Workbook
Name Slicer_Customer_Type: #N/A
Name Slicer_Region: #N/A
Name Slicer_Sale_Date__Month: #N/A
Name Slicer_Sales_Channel: #N/A

Sheet DASHBOARD

Sheet Cleaned Sales
A1: Product_ID | B1: Sale_Date | C1: Sales_Rep | D1: Region | E1: Sales_Amount | F1: Quantity_Sold | G1: Product_Category | H1: Unit_Cost | I1: Unit_Price | J1: Customer_Type | K1: Discount | L1: Payment_Method | M1: Sales_Channel
A2: 1052 | B2: 45235 | C2: =IF(ISBLANK(Table14[[#This Row],[Sales_Rep]]),"Unknown",Table14[[#This Row],[Sales_Rep]]) -> David | D2: =PROPER(Table14[[#This Row],[Region]]) -> East | E2: =IF(ISBLANK(Table14[[#This Row],[Sales_Amount]]),MEDIAN(Table14[Sales_Amount]),Table14[[#This Row],[Sales_Amount]]) -> 71951.51 | F2: =IF(ISBLANK(Table14[[#This Row],[Quantity_Sold]]),MEDIAN(Table14[Quantity_Sold]),Table14[[#This Row],[Quantity_Sold]]) -> 48 | G2: =TRIM(Table14[[#This Row],[Product_Category]]) -> Food | H2: 1147.38 | I2: 1594.67 | J2: =PROPER(Table14[[#This Row],[Customer_Type]]) -> Returning | K2: =IF(ISBLANK(Table14[[#This Row],[Discount]]),MEDIAN(Table14[Discount]),Table14[[#This Row],[Discount]]) -> 0.06 | L2: Credit Card | M2: Retail
A3: 1301 | B3: 45344 | C3: =IF(ISBLANK(Table14[[#This Row],[Sales_Rep]]),"Unknown",Table14[[#This Row],[Sales_Rep]]) -> Unknown | D3: =PROPER(Table14[[#This Row],[Region]]) -> North | E3: =IF(ISBLANK(Table14[[#This Row],[Sales_Amount]]),MEDIAN(Table14[Sales_Amount]),Table14[[#This Row],[Sales_Amount]]) -> 8444.02 | F3: =IF(ISBLANK(Table14[[#This Row],[Quantity_Sold]]),MEDIAN(Table14[Quantity_Sold]),Table14[[#This Row],[Quantity_Sold]]) -> 20 | G3: =TRIM(Table14[[#This Row],[Product_Category]]) -> Electronics | H3: 451.85 | I3: 586.39 | J3: =PROPER(Table14[[#This Row],[Customer_Type]]) -> Returning | K3: =IF(ISBLANK(Table14[[#This Row],[Discount]]),MEDIAN(Table14[Discount]),Table14[[#This Row],[Discount]]) -> 0.15 | L3: Credit Card | M3: Online
A4: 1426 | B4: 44955 | C4: =IF(ISBLANK(Table14[[#This Row],[Sales_Rep]]),"Unknown",Table14[[#This Row],[Sales_Rep]]) -> Charlie | D4: =PROPER(Table14[[#This Row],[Region]]) -> East | E4: =IF(ISBLANK(Table14[[#This Row],[Sales_Amount]]),MEDIAN(Table14[Sales_Amount]),Table14[[#This Row],[Sales_Amount]]) -> 50770.89 | F4: =IF(ISBLANK(Table14[[#This Row],[Quantity_Sold]]),MEDIAN(Table14[Quantity_Sold]),Table14[[#This Row],[Quantity_Sold]]) -> 36 | G4: =TRIM(Table14[[#This Row],[Product_Category]]) -> Clothing | H4: 1554.12 | I4: 2130.42 | J4: =PROPER(Table14[[#This Row],[Customer_Type]]) -> New | K4: =IF(ISBLANK(Table14[[#This Row],[Discount]]),MEDIAN(Table14[Discount]),Table14[[#This Row],[Discount]]) -> 0.28 | L4: Bank Transfer | M4: Retail
A5: 1170 | B5: 44981 | C5: =IF(ISBLANK(Table14[[#This Row],[Sales_Rep]]),"Unknown",Table14[[#This Row],[Sales_Rep]]) -> Eve | D5: =PROPER(Table14[[#This Row],[Region]]) -> West | E5: =IF(ISBLANK(Table14[[#This Row],[Sales_Amount]]),MEDIAN(Table14[Sales_Amount]),Table14[[#This Row],[Sales_Amount]]) -> 73691.05 | F5: =IF(ISBLANK(Table14[[#This Row],[Quantity_Sold]]),MEDIAN(Table14[Quantity_Sold]),Table14[[#This Row],[Quantity_Sold]]) -> 25 | G5: =TRIM(Table14[[#This Row],[Product_Category]]) -> Clothing | H5: 1733.8 | I5: 2477.01 | J5: =PROPER(Table14[[#This Row],[Customer_Type]]) -> Returning | K5: =IF(ISBLANK(Table14[[#This Row],[Discount]]),MEDIAN(Table14[Discount]),Table14[[#This Row],[Discount]]) -> 0.15 | L5: Credit Card | M5: Online
A6: 1019 | B6: 45263 | C6: =IF(ISBLANK(Table14[[#This Row],[Sales_Rep]]),"Unknown",Table14[[#This Row],[Sales_Rep]]) -> Eve | D6: =PROPER(Table14[[#This Row],[Region]]) -> East | E6: =IF(ISBLANK(Table14[[#This Row],[Sales_Amount]]),MEDIAN(Table14[Sales_Amount]),Table14[[#This Row],[Sales_Amount]]) -> 99978.16 | F6: =IF(ISBLANK(Table14[[#This Row],[Quantity_Sold]]),MEDIAN(Table14[Quantity_Sold]),Table14[[#This Row],[Quantity_Sold]]) -> 33 | G6: =TRIM(Table14[[#This Row],[Product_Category]]) -> Furniture | H6: 2593.01 | I6: 3650.17 | J6: =PROPER(Table14[[#This Row],[Customer_Type]]) -> Returning | K6: =IF(ISBLANK(Table14[[#This Row],[Discount]]),MEDIAN(Table14[Discount]),Table14[[#This Row],[Discount]]) -> 0.17 | L6: Credit Card | M6: Retail
A7: 1239 | B7: 45630 | C7: =IF(ISBLANK(Table14[[#This Row],[Sales_Rep]]),"Unknown",Table14[[#This Row],[Sales_Rep]]) -> Bob | D7: =PROPER(Table14[[#This Row],[Region]]) -> North | E7: =IF(ISBLANK(Table14[[#This Row],[Sales_Amount]]),MEDIAN(Table14[Sales_Amount]),Table14[[#This Row],[Sales_Amount]]) -> 18064.11 | F7: =IF(ISBLANK(Table14[[#This Row],[Quantity_Sold]]),MEDIAN(Table14[Quantity_Sold]),Table14[[#This Row],[Quantity_Sold]]) -> 12 | G7: =TRIM(Table14[[#This Row],[Product_Category]]) -> Clothing | H7: 1528.85 | I7: 1954.99 | J7: =PROPER(Table14[[#This Row],[Customer_Type]]) -> New | K7: =IF(ISBLANK(Table14[[#This Row],[Discount]]),MEDIAN(Table14[Discount]),Table14[[#This Row],[Discount]]) -> 0.23 | L7: Bank Transfer | M7: Retail
A8: 1452 | B8: 45010 | C8: =IF(ISBLANK(Table14[[#This Row],[Sales_Rep]]),"Unknown",Table14[[#This Row],[Sales_Rep]]) -> Unknown | D8: =PROPER(Table14[[#This Row],[Region]]) -> East | E8: =IF(ISBLANK(Table14[[#This Row],[Sales_Amount]]),MEDIAN(Table14[Sales_Amount]),Table14[[#This Row],[Sales_Amount]]) -> 61782.11 | F8: =IF(ISBLANK(Table14[[#This Row],[Quantity_Sold]]),MEDIAN(Table14[Quantity_Sold]),Table14[[#This Row],[Quantity_Sold]]) -> 15 | G8: =TRIM(Table14[[#This Row],[Product_Category]]) -> Food | H8: 4099.54 | I8: 5213.68 | J8: =PROPER(Table14[[#This Row],[Customer_Type]]) -> Returning | K8: =IF(ISBLANK(Table14[[#This Row],[Discount]]),MEDIAN(Table14[Discount]),Table14[[#This Row],[Discount]]) -> 0.21 | L8: Credit Card | M8: Retail
A9: 1318 | B9: 45124 | C9: =IF(ISBLANK(Table14[[#This Row],[Sales_Rep]]),"Unknown",Table14[[#This Row],[Sales_Rep]]) -> Charlie | D9: =PROPER(Table14[[#This Row],[Region]]) -> East | E9: =IF(ISBLANK(Table14[[#This Row],[Sales_Amount]]),MEDIAN(Table14[Sales_Amount]),Table14[[#This Row],[Sales_Amount]]) -> 160204.34 | F9: =IF(ISBLANK(Table14[[#This Row],[Quantity_Sold]]),MEDIAN(Table14[Quantity_Sold]),Table14[[#This Row],[Quantity_Sold]]) -> 45 | G9: =TRIM(Table14[[#This Row],[Product_Category]]) -> Food | H9: 2736.72 | I9: 3747.47 | J9: =PROPER(Table14[[#This Row],[Customer_Type]]) -> New | K9: =IF(ISBLANK(Table14[[#This Row],[Discount]]),MEDIAN(Table14[Discount]),Table14[[#This Row],[Discount]]) -> 0.15 | L9: Credit Card | M9: Online
A10: 1463 | B10: 45192 | C10: =IF(ISBLANK(Table14[[#This Row],[Sales_Rep]]),"Unknown",Table14[[#This Row],[Sales_Rep]]) -> Charlie | D10: =PROPER(Table14[[#This Row],[Region]]) -> East | E10: =IF(ISBLANK(Table14[[#This Row],[Sales_Amount]]),MEDIAN(Table14[Sales_Amount]),Table14[[#This Row],[Sales_Amount]]) -> 29967.11 | F10: =IF(ISBLANK(Table14[[#This Row],[Quantity_Sold]]),MEDIAN(Table14[Quantity_Sold]),Table14[[#This Row],[Quantity_Sold]]) -> 18 | G10: =TRIM(Table14[[#This Row],[Product_Category]]) -> Electronics | H10: 1686.82 | I10: 1935.86 | J10: =PROPER(Table14[[#This Row],[Customer_Type]]) -> Returning | K10: =IF(ISBLANK(Table14[[#This Row],[Discount]]),MEDIAN(Table14[Discount]),Table14[[#This Row],[Discount]]) -> 0.15 | L10: Bank Transfer | M10: Online
A11: 1427 | B11: 45297 | C11: =IF(ISBLANK(Table14[[#This Row],[Sales_Rep]]),"Unknown",Table14[[#This Row],[Sales_Rep]]) -> Eve | D11: =PROPER(Table14[[#This Row],[Region]]) -> West | E11: =IF(ISBLANK(Table14[[#This Row],[Sales_Amount]]),MEDIAN(Table14[Sales_Amount]),Table14[[#This Row],[Sales_Amount]]) -> 68837.01 | F11: =IF(ISBLANK(Table14[[#This Row],[Quantity_Sold]]),MEDIAN(Table14[Quantity_Sold]),Table14[[#This Row],[Quantity_Sold]]) -> 28 | G11: =TRIM(Table14[[#This Row],[Product_Category]]) -> Food | H11: 2549.57 | I11: 3367.76 | J11: =PROPER(Table14[[#This Row],[Customer_Type]]) -> Returning | K11: =IF(ISBLANK(Table14[[#This Row],[Discount]]),MEDIAN(Table14[Discount]),Table14[[#This Row],[Discount]]) -> 0.27 | L11: Credit Card | M11: Retail
A12: 1455 | B12: 45319 | C12: =IF(ISBLANK(Table14[[#This Row],[Sales_Rep]]),"Unknown",Table14[[#This Row],[Sales_Rep]]) -> David | D12: =PROPER(Table14[[#This Row],[Region]]) -> South | E12: =IF(ISBLANK(Table14[[#This Row],[Sales_Amount]]),MEDIAN(Table14[Sales_Amount]),Table14[[#This Row],[Sales_Amount]]) -> 50770.89 | F12: =IF(ISBLANK(Table14[[#This Row],[Quantity_Sold]]),MEDIAN(Table14[Quantity_Sold]),Table14[[#This Row],[Quantity_Sold]]) -> 50 | G12: =TRIM(Table14[[#This Row],[Product_Category]]) -> Clothing | H12: 3254.81 | I12: 4805.11 | J12: =PROPER(Table14[[#This Row],[Customer_Type]]) -> Returning | K12: =IF(ISBLANK(Table14[[#This Row],[Discount]]),MEDIAN(Table14[Discount]),Table14[[#This Row],[Discount]]) -> 0.17 | L12: Cash | M12: Retail
A13: 1409 | B13: 45318 | C13: =IF(ISBLANK(Table14[[#This Row],[Sales_Rep]]),"Unknown",Table14[[#This Row],[Sales_Rep]]) -> Unknown | D13: =PROPER(Table14[[#This Row],[Region]]) -> South | E13: =IF(ISBLANK(Table14[[#This Row],[Sales_Amount]]),MEDIAN(Table14[Sales_Amount]),Table14[[#This Row],[Sales_Amount]]) -> 4650.09 | F13: =IF(ISBLANK(Table14[[#This Row],[Quantity_Sold]]),MEDIAN(Table14[Quantity_Sold]),Table14[[#This Row],[Quantity_Sold]]) -> 25 | G13: =TRIM(Table14[[#This Row],[Product_Category]]) -> Electronics | H13: 3767.42 | I13: 4744.99 | J13: =PROPER(Table14[[#This Row],[Customer_Type]]) -> Returning | K13: =IF(ISBLANK(Table14[[#This Row],[Discount]]),MEDIAN(Table14[Discount]),Table14[[#This Row],[Discount]]) -> 0.02 | L13: Cash | M13: Retail
... A409: 1316 | B409: 45573 | C409: =IF(ISBLANK(Table14[[#This Row],[Sales_Rep]]),"Unknown",Table14[[#This Row],[Sales_Rep]]) -> David | D409: =PROPER(Table14[[#This Row],[Region]]) -> South | E409: =IF(ISBLANK(Table14[[#This Row],[Sales_Amount]]),MEDIAN(Table14[Sales_Amount]),Table14[[#This Row],[Sales_Amount]]) -> 37152.72 | F409: =IF(ISBLANK(Table14[[#This Row],[Quantity_Sold]]),MEDIAN(Table14[Quantity_Sold]),Table14[[#This Row],[Quantity_Sold]]) -> 45 | G409: =TRIM(Table14[[#This Row],[Product_Category]]) -> Furniture | H409: 817.38 | I409: 938.2 | J409: =PROPER(Table14[[#This Row],[Customer_Type]]) -> Returning | K409: =IF(ISBLANK(Table14[[#This Row],[Discount]]),MEDIAN(Table14[Discount]),Table14[[#This Row],[Discount]]) -> 0.12 | L409: Bank Transfer | M409: Online
A410: 1346 | B410: 45640 | C410: =IF(ISBLANK(Table14[[#This Row],[Sales_Rep]]),"Unknown",Table14[[#This Row],[Sales_Rep]]) -> Eve | D410: East | E410: =IF(ISBLANK(Table14[[#This Row],[Sales_Amount]]),MEDIAN(Table14[Sales_Amount]),Table14[[#This Row],[Sales_Amount]]) -> 2026.33 | F410: =IF(ISBLANK(Table14[[#This Row],[Quantity_Sold]]),MEDIAN(Table14[Quantity_Sold]),Table14[[#This Row],[Quantity_Sold]]) -> 7 | G410: =TRIM(Table14[[#This Row],[Product_Category]]) -> Furniture | H410: 274.96 | I410: 332.73 | J410: =PROPER(Table14[[#This Row],[Customer_Type]]) -> Returning | K410: =IF(ISBLANK(Table14[[#This Row],[Discount]]),MEDIAN(Table14[Discount]),Table14[[#This Row],[Discount]]) -> 0.13 | L410: Cash | M410: Retail
A411: 1280 | B411: 45496 | C411: =IF(ISBLANK(Table14[[#This Row],[Sales_Rep]]),"Unknown",Table14[[#This Row],[Sales_Rep]]) -> David | D411: =PROPER(Table14[[#This Row],[Region]]) -> East | E411: =IF(ISBLANK(Table14[[#This Row],[Sales_Amount]]),MEDIAN(Table14[Sales_Amount]),Table14[[#This Row],[Sales_Amount]]) -> 27005.66 | F411: =IF(ISBLANK(Table14[[#This Row],[Quantity_Sold]]),MEDIAN(Table14[Quantity_Sold]),Table14[[#This Row],[Quantity_Sold]]) -> 22 | G411: =TRIM(Table14[[#This Row],[Product_Category]]) -> Clothing | H411: 951.45 | I411: 1227.53 | J411: =PROPER(Table14[[#This Row],[Customer_Type]]) -> Returning | K411: =IF(ISBLANK(Table14[[#This Row],[Discount]]),MEDIAN(Table14[Discount]),Table14[[#This Row],[Discount]]) -> 0 | L411: Bank Transfer | M411: Online
A412: 1004 | B412: 45575 | C412: =IF(ISBLANK(Table14[[#This Row],[Sales_Rep]]),"Unknown",Table14[[#This Row],[Sales_Rep]]) -> Bob | D412: =PROPER(Table14[[#This Row],[Region]]) -> North | E412: =IF(ISBLANK(Table14[[#This Row],[Sales_Amount]]),MEDIAN(Table14[Sales_Amount]),Table14[[#This Row],[Sales_Amount]]) -> 160343.9 | F412: =IF(ISBLANK(Table14[[#This Row],[Quantity_Sold]]),MEDIAN(Table14[Quantity_Sold]),Table14[[#This Row],[Quantity_Sold]]) -> 39 | G412: =TRIM(Table14[[#This Row],[Product_Category]]) -> Clothing | H412: 3562.56 | I412: 4836.92 | J412: =PROPER(Table14[[#This Row],[Customer_Type]]) -> Returning | K412: =IF(ISBLANK(Table14[[#This Row],[Discount]]),MEDIAN(Table14[Discount]),Table14[[#This Row],[Discount]]) -> 0.15 | L412: Credit Card | M412: Retail
A413: 1107 | B413: 45482 | C413: =IF(ISBLANK(Table14[[#This Row],[Sales_Rep]]),"Unknown",Table14[[#This Row],[Sales_Rep]]) -> Bob | D413: =PROPER(Table14[[#This Row],[Region]]) -> East | E413: =IF(ISBLANK(Table14[[#This Row],[Sales_Amount]]),MEDIAN(Table14[Sales_Amount]),Table14[[#This Row],[Sales_Amount]]) -> 16395.28 | F413: =IF(ISBLANK(Table14[[#This Row],[Quantity_Sold]]),MEDIAN(Table14[Quantity_Sold]),Table14[[#This Row],[Quantity_Sold]]) -> 6 | G413: =TRIM(Table14[[#This Row],[Product_Category]]) -> Food | H413: 2278.1 | I413: 3214.76 | J413: =PROPER(Table14[[#This Row],[Customer_Type]]) -> Returning | K413: =IF(ISBLANK(Table14[[#This Row],[Discount]]),MEDIAN(Table14[Discount]),Table14[[#This Row],[Discount]]) -> 0.15 | L413: Credit Card | M413: Retail
A414: 1259 | B414: 45240 | C414: =IF(ISBLANK(Table14[[#This Row],[Sales_Rep]]),"Unknown",Table14[[#This Row],[Sales_Rep]]) -> Eve | D414: =PROPER(Table14[[#This Row],[Region]]) -> East | E414: =IF(ISBLANK(Table14[[#This Row],[Sales_Amount]]),MEDIAN(Table14[Sales_Amount]),Table14[[#This Row],[Sales_Amount]]) -> 36234.89 | F414: =IF(ISBLANK(Table14[[#This Row],[Quantity_Sold]]),MEDIAN(Table14[Quantity_Sold]),Table14[[#This Row],[Quantity_Sold]]) -> 9 | G414: =TRIM(Table14[[#This Row],[Product_Category]]) -> Food | H414: 4603.19 | I414: 5751.57 | J414: =PROPER(Table14[[#This Row],[Customer_Type]]) -> Returning | K414: =IF(ISBLANK(Table14[[#This Row],[Discount]]),MEDIAN(Table14[Discount]),Table14[[#This Row],[Discount]]) -> 0.3 | L414: Cash | M414: Retail
A415: 1229 | B415: 45609 | C415: =IF(ISBLANK(Table14[[#This Row],[Sales_Rep]]),"Unknown",Table14[[#This Row],[Sales_Rep]]) -> David | D415: =PROPER(Table14[[#This Row],[Region]]) -> North | E415: =IF(ISBLANK(Table14[[#This Row],[Sales_Amount]]),MEDIAN(Table14[Sales_Amount]),Table14[[#This Row],[Sales_Amount]]) -> 50490.94 | F415: =IF(ISBLANK(Table14[[#This Row],[Quantity_Sold]]),MEDIAN(Table14[Quantity_Sold]),Table14[[#This Row],[Quantity_Sold]]) -> 25 | G415: =TRIM(Table14[[#This Row],[Product_Category]]) -> Electronics | H415: 1112.64 | I415: 1471.61 | J415: =PROPER(Table14[[#This Row],[Customer_Type]]) -> New | K415: =IF(ISBLANK(Table14[[#This Row],[Discount]]),MEDIAN(Table14[Discount]),Table14[[#This Row],[Discount]]) -> 0.27 | L415: Cash | M415: Online
A416: 1181 | B416: 45384 | C416: =IF(ISBLANK(Table14[[#This Row],[Sales_Rep]]),"Unknown",Table14[[#This Row],[Sales_Rep]]) -> Alice | D416: =PROPER(Table14[[#This Row],[Region]]) -> West | E416: =IF(ISBLANK(Table14[[#This Row],[Sales_Amount]]),MEDIAN(Table14[Sales_Amount]),Table14[[#This Row],[Sales_Amount]]) -> 86255.95 | F416: =IF(ISBLANK(Table14[[#This Row],[Quantity_Sold]]),MEDIAN(Table14[Quantity_Sold]),Table14[[#This Row],[Quantity_Sold]]) -> 48 | G416: =TRIM(Table14[[#This Row],[Product_Category]]) -> Clothing | H416: 1427.6 | I416: 2019.1 | J416: =PROPER(Table14[[#This Row],[Customer_Type]]) -> Returning | K416: =IF(ISBLANK(Table14[[#This Row],[Discount]]),MEDIAN(Table14[Discount]),Table14[[#This Row],[Discount]]) -> 0.11 | L416: Cash | M416: Retail
A417: 1340 | B417: 45433 | C417: =IF(ISBLANK(Table14[[#This Row],[Sales_Rep]]),"Unknown",Table14[[#This Row],[Sales_Rep]]) -> Eve | D417: =PROPER(Table14[[#This Row],[Region]]) -> East | E417: =IF(ISBLANK(Table14[[#This Row],[Sales_Amount]]),MEDIAN(Table14[Sales_Amount]),Table14[[#This Row],[Sales_Amount]]) -> 1986.17 | F417: =IF(ISBLANK(Table14[[#This Row],[Quantity_Sold]]),MEDIAN(Table14[Quantity_Sold]),Table14[[#This Row],[Quantity_Sold]]) -> 23 | G417: =TRIM(Table14[[#This Row],[Product_Category]]) -> Furniture | H417: 80.79 | I417: 90.9 | J417: =PROPER(Table14[[#This Row],[Customer_Type]]) -> Returning | K417: =IF(ISBLANK(Table14[[#This Row],[Discount]]),MEDIAN(Table14[Discount]),Table14[[#This Row],[Discount]]) -> 0.05 | L417: Credit Card | M417: Online
A418: 1182 | B418: 45509 | C418: =IF(ISBLANK(Table14[[#This Row],[Sales_Rep]]),"Unknown",Table14[[#This Row],[Sales_Rep]]) -> Bob | D418: =PROPER(Table14[[#This Row],[Region]]) -> North | E418: =IF(ISBLANK(Table14[[#This Row],[Sales_Amount]]),MEDIAN(Table14[Sales_Amount]),Table14[[#This Row],[Sales_Amount]]) -> 68193.22 | F418: =IF(ISBLANK(Table14[[#This Row],[Quantity_Sold]]),MEDIAN(Table14[Quantity_Sold]),Table14[[#This Row],[Quantity_Sold]]) -> 28 | G418: =TRIM(Table14[[#This Row],[Product_Category]]) -> Clothing | H418: 2942.48 | I418: 3382.6 | J418: =PROPER(Table14[[#This Row],[Customer_Type]]) -> New | K418: =IF(ISBLANK(Table14[[#This Row],[Discount]]),MEDIAN(Table14[Discount]),Table14[[#This Row],[Discount]]) -> 0.28 | L418: Credit Card | M418: Online
A419: 1411 | B419: 45478 | C419: =IF(ISBLANK(Table14[[#This Row],[Sales_Rep]]),"Unknown",Table14[[#This Row],[Sales_Rep]]) -> Bob | D419: =PROPER(Table14[[#This Row],[Region]]) -> East | E419: =IF(ISBLANK(Table14[[#This Row],[Sales_Amount]]),MEDIAN(Table14[Sales_Amount]),Table14[[#This Row],[Sales_Amount]]) -> 144251.98 | F419: =IF(ISBLANK(Table14[[#This Row],[Quantity_Sold]]),MEDIAN(Table14[Quantity_Sold]),Table14[[#This Row],[Quantity_Sold]]) -> 49 | G419: =TRIM(Table14[[#This Row],[Product_Category]]) -> Furniture | H419: 2525.82 | I419: 3271.02 | J419: =PROPER(Table14[[#This Row],[Customer_Type]]) -> New | K419: =IF(ISBLANK(Table14[[#This Row],[Discount]]),MEDIAN(Table14[Discount]),Table14[[#This Row],[Discount]]) -> 0.1 | L419: Bank Transfer | M419: Online
A420: 1241 | B420: 45327 | C420: =IF(ISBLANK(Table14[[#This Row],[Sales_Rep]]),"Unknown",Table14[[#This Row],[Sales_Rep]]) -> Eve | D420: =PROPER(Table14[[#This Row],[Region]]) -> South | E420: =IF(ISBLANK(Table14[[#This Row],[Sales_Amount]]),MEDIAN(Table14[Sales_Amount]),Table14[[#This Row],[Sales_Amount]]) -> 90816.88 | F420: =IF(ISBLANK(Table14[[#This Row],[Quantity_Sold]]),MEDIAN(Table14[Quantity_Sold]),Table14[[#This Row],[Quantity_Sold]]) -> 15 | G420: =TRIM(Table14[[#This Row],[Product_Category]]) -> Food | H420: 4420.32 | I420: 6241.71 | J420: =PROPER(Table14[[#This Row],[Customer_Type]]) -> Returning | K420: =IF(ISBLANK(Table14[[#This Row],[Discount]]),MEDIAN(Table14[Discount]),Table14[[#This Row],[Discount]]) -> 0.03 | L420: Bank Transfer | M420: Retail
A421: 1464 | B421: 45216 | C421: =IF(ISBLANK(Table14[[#This Row],[Sales_Rep]]),"Unknown",Table14[[#This Row],[Sales_Rep]]) -> David | D421: =PROPER(Table14[[#This Row],[Region]]) -> North | E421: =IF(ISBLANK(Table14[[#This Row],[Sales_Amount]]),MEDIAN(Table14[Sales_Amount]),Table14[[#This Row],[Sales_Amount]]) -> 27506.45 | F421: =IF(ISBLANK(Table14[[#This Row],[Quantity_Sold]]),MEDIAN(Table14[Quantity_Sold]),Table14[[#This Row],[Quantity_Sold]]) -> 8 | G421: =TRIM(Table14[[#This Row],[Product_Category]]) -> Clothing | H421: 2970.29 | I421: 3820.34 | J421: =PROPER(Table14[[#This Row],[Customer_Type]]) -> New | K421: =IF(ISBLANK(Table14[[#This Row],[Discount]]),MEDIAN(Table14[Discount]),Table14[[#This Row],[Discount]]) -> 0.1 | L421: Cash | M421: Retail
A422: 1223 | B422: 44991 | C422: =IF(ISBLANK(Table14[[#This Row],[Sales_Rep]]),"Unknown",Table14[[#This Row],[Sales_Rep]]) -> Bob | D422: =PROPER(Table14[[#This Row],[Region]]) -> East | E422: =IF(ISBLANK(Table14[[#This Row],[Sales_Amount]]),MEDIAN(Table14[Sales_Amount]),Table14[[#This Row],[Sales_Amount]]) -> 53754.5 | F422: =IF(ISBLANK(Table14[[#This Row],[Quantity_Sold]]),MEDIAN(Table14[Quantity_Sold]),Table14[[#This Row],[Quantity_Sold]]) -> 16 | G422: =TRIM(Table14[[#This Row],[Product_Category]]) -> Electronics | H422: 2897.26 | I422: 3651.8 | J422: =PROPER(Table14[[#This Row],[Customer_Type]]) -> Returning | K422: =IF(ISBLANK(Table14[[#This Row],[Discount]]),MEDIAN(Table14[Discount]),Table14[[#This Row],[Discount]]) -> 0.08 | L422: Credit Card | M422: Retail
... A4551: 1267 | B4551: 44961 | C4551: =IF(ISBLANK(Table14[[#This Row],[Sales_Rep]]),"Unknown",Table14[[#This Row],[Sales_Rep]]) -> David | D4551: =PROPER(Table14[[#This Row],[Region]]) -> East | E4551: =IF(ISBLANK(Table14[[#This Row],[Sales_Amount]]),MEDIAN(Table14[Sales_Amount]),Table14[[#This Row],[Sales_Amount]]) -> 5962.63 | F4551: =IF(ISBLANK(Table14[[#This Row],[Quantity_Sold]]),MEDIAN(Table14[Quantity_Sold]),Table14[[#This Row],[Quantity_Sold]]) -> 2 | G4551: =TRIM(Table14[[#This Row],[Product_Category]]) -> Furniture | H4551: 3322.09 | I4551: 4259.02 | J4551: =PROPER(Table14[[#This Row],[Customer_Type]]) -> Returning | K4551: =IF(ISBLANK(Table14[[#This Row],[Discount]]),MEDIAN(Table14[Discount]),Table14[[#This Row],[Discount]]) -> 0.3 | L4551: Credit Card | M4551: Retail

Sheet KPI cards
A1: Total sales | B1: =SUM('Cleaned Sales'!E2:E4551) -> 3.2085111e+08
A2: Total Orders | B2: =COUNTA('Cleaned Sales'!A2:A4551) -> 4550
A3: AVG discount | B3: =AVERAGE('Cleaned Sales'!K2:K4551) -> 0.1503033
A4: Top selling category | B4: =INDEX('Sales by product category'!A4:A7,MATCH(MAX('Sales by product category'!B4:B7),'Sales by product category'!B4:B7,0)) -> Electronics
A5: Average Order Value | B5: =AVERAGE('Cleaned Sales'!E2:E4551) -> 70516.729

Sheet Cleaned Using formulas
A1: Product_ID | B1: Sale_Date | C1: Sales_Rep | D1: Region | E1: Sales_Amount | F1: Quantity_Sold | G1: Product_Category | H1: Unit_Cost | I1: Unit_Price | J1: Customer_Type | K1: Discount | L1: Payment_Method | M1: Sales_Channel | N1: Sales_Rep2 | O1: Region | P1: Sales_Amount | Q1: Quantity_Sold | R1: Product_Category | S1: Customer_Type | T1: Discount
A2: 1052 | B2: 45235 | C2: David | D2: East | E2: 71951.51 | F2: 48 | G2: Food | H2: 1147.38 | I2: 1594.67 | J2: ReturninG | K2: 0.06 | L2: Credit Card | M2: Retail | N2: =IF(ISBLANK(Table14[[#This Row],[Sales_Rep]]),"Unknown",Table14[[#This Row],[Sales_Rep]]) -> David | O2: =PROPER(Table14[[#This Row],[Region]]) -> East | P2: =IF(ISBLANK(Table14[[#This Row],[Sales_Amount]]),MEDIAN(Table14[Sales_Amount]),Table14[[#This Row],[Sales_Amount]]) -> 71951.51 | Q2: =IF(ISBLANK(Table14[[#This Row],[Quantity_Sold]]),MEDIAN(Table14[Quantity_Sold]),Table14[[#This Row],[Quantity_Sold]]) -> 48 | R2: =TRIM(Table14[[#This Row],[Product_Category]]) -> Food | S2: =PROPER(Table14[[#This Row],[Customer_Type]]) -> Returning | T2: =IF(ISBLANK(Table14[[#This Row],[Discount]]),MEDIAN(Table14[Discount]),Table14[[#This Row],[Discount]]) -> 0.06
A3: 1301 | B3: 45344 | D3: NORTH | E3: 8444.02 | F3: 20 | G3: Electronics | H3: 451.85 | I3: 586.39 | J3: returning | L3: Credit Card | M3: Online | N3: =IF(ISBLANK(Table14[[#This Row],[Sales_Rep]]),"Unknown",Table14[[#This Row],[Sales_Rep]]) -> Unknown | O3: =PROPER(Table14[[#This Row],[Region]]) -> North | P3: =IF(ISBLANK(Table14[[#This Row],[Sales_Amount]]),MEDIAN(Table14[Sales_Amount]),Table14[[#This Row],[Sales_Amount]]) -> 8444.02 | Q3: =IF(ISBLANK(Table14[[#This Row],[Quantity_Sold]]),MEDIAN(Table14[Quantity_Sold]),Table14[[#This Row],[Quantity_Sold]]) -> 20 | R3: =TRIM(Table14[[#This Row],[Product_Category]]) -> Electronics | S3: =PROPER(Table14[[#This Row],[Customer_Type]]) -> Returning | T3: =IF(ISBLANK(Table14[[#This Row],[Discount]]),MEDIAN(Table14[Discount]),Table14[[#This Row],[Discount]]) -> 0.15
A4: 1426 | B4: 44955 | C4: Charlie | D4: East | F4: 36 | G4: Clothing | H4: 1554.12 | I4: 2130.42 | J4: New | K4: 0.28 | L4: Bank Transfer | M4: Retail | N4: =IF(ISBLANK(Table14[[#This Row],[Sales_Rep]]),"Unknown",Table14[[#This Row],[Sales_Rep]]) -> Charlie | O4: =PROPER(Table14[[#This Row],[Region]]) -> East | P4: =IF(ISBLANK(Table14[[#This Row],[Sales_Amount]]),MEDIAN(Table14[Sales_Amount]),Table14[[#This Row],[Sales_Amount]]) -> 50770.89 | Q4: =IF(ISBLANK(Table14[[#This Row],[Quantity_Sold]]),MEDIAN(Table14[Quantity_Sold]),Table14[[#This Row],[Quantity_Sold]]) -> 36 | R4: =TRIM(Table14[[#This Row],[Product_Category]]) -> Clothing | S4: =PROPER(Table14[[#This Row],[Customer_Type]]) -> New | T4: =IF(ISBLANK(Table14[[#This Row],[Discount]]),MEDIAN(Table14[Discount]),Table14[[#This Row],[Discount]]) -> 0.28
A5: 1170 | B5: 44981 | C5: Eve | D5: West | E5: 73691.05 | G5: Clothing | H5: 1733.8 | I5: 2477.01 | J5: rEturning | K5: 0.15 | L5: Credit Card | M5: Online | N5: =IF(ISBLANK(Table14[[#This Row],[Sales_Rep]]),"Unknown",Table14[[#This Row],[Sales_Rep]]) -> Eve | O5: =PROPER(Table14[[#This Row],[Region]]) -> West | P5: =IF(ISBLANK(Table14[[#This Row],[Sales_Amount]]),MEDIAN(Table14[Sales_Amount]),Table14[[#This Row],[Sales_Amount]]) -> 73691.05 | Q5: =IF(ISBLANK(Table14[[#This Row],[Quantity_Sold]]),MEDIAN(Table14[Quantity_Sold]),Table14[[#This Row],[Quantity_Sold]]) -> 25 | R5: =TRIM(Table14[[#This Row],[Product_Category]]) -> Clothing | S5: =PROPER(Table14[[#This Row],[Customer_Type]]) -> Returning | T5: =IF(ISBLANK(Table14[[#This Row],[Discount]]),MEDIAN(Table14[Discount]),Table14[[#This Row],[Discount]]) -> 0.15
A6: 1019 | B6: 45263 | C6: Eve | D6: East | E6: 99978.16 | F6: 33 | G6: Furniture | H6: 2593.01 | I6: 3650.17 | J6: Returning | K6: 0.17 | L6: Credit Card | M6: Retail | N6: =IF(ISBLANK(Table14[[#This Row],[Sales_Rep]]),"Unknown",Table14[[#This Row],[Sales_Rep]]) -> Eve | O6: =PROPER(Table14[[#This Row],[Region]]) -> East | P6: =IF(ISBLANK(Table14[[#This Row],[Sales_Amount]]),MEDIAN(Table14[Sales_Amount]),Table14[[#This Row],[Sales_Amount]]) -> 99978.16 | Q6: =IF(ISBLANK(Table14[[#This Row],[Quantity_Sold]]),MEDIAN(Table14[Quantity_Sold]),Table14[[#This Row],[Quantity_Sold]]) -> 33 | R6: =TRIM(Table14[[#This Row],[Product_Category]]) -> Furniture | S6: =PROPER(Table14[[#This Row],[Customer_Type]]) -> Returning | T6: =IF(ISBLANK(Table14[[#This Row],[Discount]]),MEDIAN(Table14[Discount]),Table14[[#This Row],[Discount]]) -> 0.17
A7: 1239 | B7: 45630 | C7: Bob | D7: NORTH | E7: 18064.11 | F7: 12 | G7: Clothing | H7: 1528.85 | I7: 1954.99 | J7: new | K7: 0.23 | L7: Bank Transfer | M7: Retail | N7: =IF(ISBLANK(Table14[[#This Row],[Sales_Rep]]),"Unknown",Table14[[#This Row],[Sales_Rep]]) -> Bob | O7: =PROPER(Table14[[#This Row],[Region]]) -> North | P7: =IF(ISBLANK(Table14[[#This Row],[Sales_Amount]]),MEDIAN(Table14[Sales_Amount]),Table14[[#This Row],[Sales_Amount]]) -> 18064.11 | Q7: =IF(ISBLANK(Table14[[#This Row],[Quantity_Sold]]),MEDIAN(Table14[Quantity_Sold]),Table14[[#This Row],[Quantity_Sold]]) -> 12 | R7: =TRIM(Table14[[#This Row],[Product_Category]]) -> Clothing | S7: =PROPER(Table14[[#This Row],[Customer_Type]]) -> New | T7: =IF(ISBLANK(Table14[[#This Row],[Discount]]),MEDIAN(Table14[Discount]),Table14[[#This Row],[Discount]]) -> 0.23
A8: 1452 | B8: 45010 | D8: East | E8: 61782.11 | F8: 15 | G8: Food | H8: 4099.54 | I8: 5213.68 | J8: returning | K8: 0.21 | L8: Credit Card | M8: Retail | N8: =IF(ISBLANK(Table14[[#This Row],[Sales_Rep]]),"Unknown",Table14[[#This Row],[Sales_Rep]]) -> Unknown | O8: =PROPER(Table14[[#This Row],[Region]]) -> East | P8: =IF(ISBLANK(Table14[[#This Row],[Sales_Amount]]),MEDIAN(Table14[Sales_Amount]),Table14[[#This Row],[Sales_Amount]]) -> 61782.11 | Q8: =IF(ISBLANK(Table14[[#This Row],[Quantity_Sold]]),MEDIAN(Table14[Quantity_Sold]),Table14[[#This Row],[Quantity_Sold]]) -> 15 | R8: =TRIM(Table14[[#This Row],[Product_Category]]) -> Food | S8: =PROPER(Table14[[#This Row],[Customer_Type]]) -> Returning | T8: =IF(ISBLANK(Table14[[#This Row],[Discount]]),MEDIAN(Table14[Discount]),Table14[[#This Row],[Discount]]) -> 0.21
A9: 1318 | B9: 45124 | C9: Charlie | D9: east | E9: 160204.34 | F9: 45 | G9: Food | H9: 2736.72 | I9: 3747.47 | J9: NeW | L9: Credit Card | M9: Online | N9: =IF(ISBLANK(Table14[[#This Row],[Sales_Rep]]),"Unknown",Table14[[#This Row],[Sales_Rep]]) -> Charlie | O9: =PROPER(Table14[[#This Row],[Region]]) -> East | P9: =IF(ISBLANK(Table14[[#This Row],[Sales_Amount]]),MEDIAN(Table14[Sales_Amount]),Table14[[#This Row],[Sales_Amount]]) -> 160204.34 | Q9: =IF(ISBLANK(Table14[[#This Row],[Quantity_Sold]]),MEDIAN(Table14[Quantity_Sold]),Table14[[#This Row],[Quantity_Sold]]) -> 45 | R9: =TRIM(Table14[[#This Row],[Product_Category]]) -> Food | S9: =PROPER(Table14[[#This Row],[Customer_Type]]) -> New | T9: =IF(ISBLANK(Table14[[#This Row],[Discount]]),MEDIAN(Table14[Discount]),Table14[[#This Row],[Discount]]) -> 0.15
A10: 1463 | B10: 45192 | C10: Charlie | D10: East | E10: 29967.11 | F10: 18 | G10: Electronics | H10: 1686.82 | I10: 1935.86 | J10: Returning | L10: Bank Transfer | M10: Online | N10: =IF(ISBLANK(Table14[[#This Row],[Sales_Rep]]),"Unknown",Table14[[#This Row],[Sales_Rep]]) -> Charlie | O10: =PROPER(Table14[[#This Row],[Region]]) -> East | P10: =IF(ISBLANK(Table14[[#This Row],[Sales_Amount]]),MEDIAN(Table14[Sales_Amount]),Table14[[#This Row],[Sales_Amount]]) -> 29967.11 | Q10: =IF(ISBLANK(Table14[[#This Row],[Quantity_Sold]]),MEDIAN(Table14[Quantity_Sold]),Table14[[#This Row],[Quantity_Sold]]) -> 18 | R10: =TRIM(Table14[[#This Row],[Product_Category]]) -> Electronics | S10: =PROPER(Table14[[#This Row],[Customer_Type]]) -> Returning | T10: =IF(ISBLANK(Table14[[#This Row],[Discount]]),MEDIAN(Table14[Discount]),Table14[[#This Row],[Discount]]) -> 0.15
A11: 1427 | B11: 45297 | C11: Eve | D11: West | E11: 68837.01 | F11: 28 | G11: Food | H11: 2549.57 | I11: 3367.76 | J11: returning | K11: 0.27 | L11: Credit Card | M11: Retail | N11: =IF(ISBLANK(Table14[[#This Row],[Sales_Rep]]),"Unknown",Table14[[#This Row],[Sales_Rep]]) -> Eve | O11: =PROPER(Table14[[#This Row],[Region]]) -> West | P11: =IF(ISBLANK(Table14[[#This Row],[Sales_Amount]]),MEDIAN(Table14[Sales_Amount]),Table14[[#This Row],[Sales_Amount]]) -> 68837.01 | Q11: =IF(ISBLANK(Table14[[#This Row],[Quantity_Sold]]),MEDIAN(Table14[Quantity_Sold]),Table14[[#This Row],[Quantity_Sold]]) -> 28 | R11: =TRIM(Table14[[#This Row],[Product_Category]]) -> Food | S11: =PROPER(Table14[[#This Row],[Customer_Type]]) -> Returning | T11: =IF(ISBLANK(Table14[[#This Row],[Discount]]),MEDIAN(Table14[Discount]),Table14[[#This Row],[Discount]]) -> 0.27
A12: 1455 | B12: 45319 | C12: David | D12: SOuth | F12: 50 | G12: Clothing | H12: 3254.81 | I12: 4805.11 | J12: ReturninG | K12: 0.17 | L12: Cash | M12: Retail | N12: =IF(ISBLANK(Table14[[#This Row],[Sales_Rep]]),"Unknown",Table14[[#This Row],[Sales_Rep]]) -> David | O12: =PROPER(Table14[[#This Row],[Region]]) -> South | P12: =IF(ISBLANK(Table14[[#This Row],[Sales_Amount]]),MEDIAN(Table14[Sales_Amount]),Table14[[#This Row],[Sales_Amount]]) -> 50770.89 | Q12: =IF(ISBLANK(Table14[[#This Row],[Quantity_Sold]]),MEDIAN(Table14[Quantity_Sold]),Table14[[#This Row],[Quantity_Sold]]) -> 50 | R12: =TRIM(Table14[[#This Row],[Product_Category]]) -> Clothing | S12: =PROPER(Table14[[#This Row],[Customer_Type]]) -> Returning | T12: =IF(ISBLANK(Table14[[#This Row],[Discount]]),MEDIAN(Table14[Discount]),Table14[[#This Row],[Discount]]) -> 0.17
A13: 1409 | B13: 45318 | D13: South | E13: 4650.09 | G13: Electronics | H13: 3767.42 | I13: 4744.99 | J13: Returning | K13: 0.02 | L13: Cash | M13: Retail | N13: =IF(ISBLANK(Table14[[#This Row],[Sales_Rep]]),"Unknown",Table14[[#This Row],[Sales_Rep]]) -> Unknown | O13: =PROPER(Table14[[#This Row],[Region]]) -> South | P13: =IF(ISBLANK(Table14[[#This Row],[Sales_Amount]]),MEDIAN(Table14[Sales_Amount]),Table14[[#This Row],[Sales_Amount]]) -> 4650.09 | Q13: =IF(ISBLANK(Table14[[#This Row],[Quantity_Sold]]),MEDIAN(Table14[Quantity_Sold]),Table14[[#This Row],[Quantity_Sold]]) -> 25 | R13: =TRIM(Table14[[#This Row],[Product_Category]]) -> Electronics | S13: =PROPER(Table14[[#This Row],[Customer_Type]]) -> Returning | T13: =IF(ISBLANK(Table14[[#This Row],[Discount]]),MEDIAN(Table14[Discount]),Table14[[#This Row],[Discount]]) -> 0.02
A14: 1169 | B14: 45480 | C14: Eve | D14: WEST | E14: 38774.35 | F14: 49 | G14: Furniture | H14: 803.61 | I14: 976.93 | J14: new | K14: 0.19 | L14: Cash | M14: Retail | N14: =IF(ISBLANK(Table14[[#This Row],[Sales_Rep]]),"Unknown",Table14[[#This Row],[Sales_Rep]]) -> Eve | O14: =PROPER(Table14[[#This Row],[Region]]) -> West | P14: =IF(ISBLANK(Table14[[#This Row],[Sales_Amount]]),MEDIAN(Table14[Sales_Amount]),Table14[[#This Row],[Sales_Amount]]) -> 38774.35 | Q14: =IF(ISBLANK(Table14[[#This Row],[Quantity_Sold]]),MEDIAN(Table14[Quantity_Sold]),Table14[[#This Row],[Quantity_Sold]]) -> 49 | R14: =TRIM(Table14[[#This Row],[Product_Category]]) -> Furniture | S14: =PROPER(Table14[[#This Row],[Customer_Type]]) -> New | T14: =IF(ISBLANK(Table14[[#This Row],[Discount]]),MEDIAN(Table14[Discount]),Table14[[#This Row],[Discount]]) -> 0.19
A15: 1177 | B15: 45506 | C15: Bob | D15: NORTH | E15: 50873.54 | F15: 15 | G15: Food | H15: 2693.32 | I15: 3768.41 | J15: New | K15: 0.1 | L15: Cash | M15: Online | N15: =IF(ISBLANK(Table14[[#This Row],[Sales_Rep]]),"Unknown",Table14[[#This Row],[Sales_Rep]]) -> Bob | O15: =PROPER(Table14[[#This Row],[Region]]) -> North | P15: =IF(ISBLANK(Table14[[#This Row],[Sales_Amount]]),MEDIAN(Table14[Sales_Amount]),Table14[[#This Row],[Sales_Amount]]) -> 50873.54 | Q15: =IF(ISBLANK(Table14[[#This Row],[Quantity_Sold]]),MEDIAN(Table14[Quantity_Sold]),Table14[[#This Row],[Quantity_Sold]]) -> 15 | R15: =TRIM(Table14[[#This Row],[Product_Category]]) -> Food | S15: =PROPER(Table14[[#This Row],[Customer_Type]]) -> New | T15: =IF(ISBLANK(Table14[[#This Row],[Discount]]),MEDIAN(Table14[Discount]),Table14[[#This Row],[Discount]]) -> 0.1
A16: 1060 | B16: 45151 | C16: David | D16: East | E16: 84654.2 | F16: 27 | G16: Electronics | H16: 3628.69 | I16: 4354.64 | J16: New | K16: 0.28 | L16: Credit Card | M16: Online | N16: =IF(ISBLANK(Table14[[#This Row],[Sales_Rep]]),"Unknown",Table14[[#This Row],[Sales_Rep]]) -> David | O16: =PROPER(Table14[[#This Row],[Region]]) -> East | P16: =IF(ISBLANK(Table14[[#This Row],[Sales_Amount]]),MEDIAN(Table14[Sales_Amount]),Table14[[#This Row],[Sales_Amount]]) -> 84654.2 | Q16: =IF(ISBLANK(Table14[[#This Row],[Quantity_Sold]]),MEDIAN(Table14[Quantity_Sold]),Table14[[#This Row],[Quantity_Sold]]) -> 27 | R16: =TRIM(Table14[[#This Row],[Product_Category]]) -> Electronics | S16: =PROPER(Table14[[#This Row],[Customer_Type]]) -> New | T16: =IF(ISBLANK(Table14[[#This Row],[Discount]]),MEDIAN(Table14[Discount]),Table14[[#This Row],[Discount]]) -> 0.28
A17: 1159 | B17: 44940 | C17: Bob | D17: East | F17: 6 | G17: Electronics | H17: 2645.44 | I17: 3000.09 | J17: ReturninG | K17: 0.15 | L17: Bank Transfer | M17: Online | N17: =IF(ISBLANK(Table14[[#This Row],[Sales_Rep]]),"Unknown",Table14[[#This Row],[Sales_Rep]]) -> Bob | O17: =PROPER(Table14[[#This Row],[Region]]) -> East | P17: =IF(ISBLANK(Table14[[#This Row],[Sales_Amount]]),MEDIAN(Table14[Sales_Amount]),Table14[[#This Row],[Sales_Amount]]) -> 50770.89 | Q17: =IF(ISBLANK(Table14[[#This Row],[Quantity_Sold]]),MEDIAN(Table14[Quantity_Sold]),Table14[[#This Row],[Quantity_Sold]]) -> 6 | R17: =TRIM(Table14[[#This Row],[Product_Category]]) -> Electronics | S17: =PROPER(Table14[[#This Row],[Customer_Type]]) -> Returning | T17: =IF(ISBLANK(Table14[[#This Row],[Discount]]),MEDIAN(Table14[Discount]),Table14[[#This Row],[Discount]]) -> 0.15
A18: 1139 | B18: 45154 | C18: David | D18: East | E18: 5218.69 | F18: 2 | G18: Electronics | H18: 2389.48 | I18: 2899.27 | J18: Returning | K18: 0.1 | L18: Bank Transfer | M18: Online | N18: =IF(ISBLANK(Table14[[#This Row],[Sales_Rep]]),"Unknown",Table14[[#This Row],[Sales_Rep]]) -> David | O18: =PROPER(Table14[[#This Row],[Region]]) -> East | P18: =IF(ISBLANK(Table14[[#This Row],[Sales_Amount]]),MEDIAN(Table14[Sales_Amount]),Table14[[#This Row],[Sales_Amount]]) -> 5218.69 | Q18: =IF(ISBLANK(Table14[[#This Row],[Quantity_Sold]]),MEDIAN(Table14[Quantity_Sold]),Table14[[#This Row],[Quantity_Sold]]) -> 2 | R18: =TRIM(Table14[[#This Row],[Product_Category]]) -> Electronics | S18: =PROPER(Table14[[#This Row],[Customer_Type]]) -> Returning | T18: =IF(ISBLANK(Table14[[#This Row],[Discount]]),MEDIAN(Table14[Discount]),Table14[[#This Row],[Discount]]) -> 0.1
A19: 1053 | B19: 44962 | D19: South | E19: 11615 | F19: 12 | G19: Furniture | H19: 882.08 | I19: 987.67 | J19: New | K19: 0.02 | L19: Bank Transfer | M19: Online | N19: =IF(ISBLANK(Table14[[#This Row],[Sales_Rep]]),"Unknown",Table14[[#This Row],[Sales_Rep]]) -> Unknown | O19: =PROPER(Table14[[#This Row],[Region]]) -> South | P19: =IF(ISBLANK(Table14[[#This Row],[Sales_Amount]]),MEDIAN(Table14[Sales_Amount]),Table14[[#This Row],[Sales_Amount]]) -> 11615 | Q19: =IF(ISBLANK(Table14[[#This Row],[Quantity_Sold]]),MEDIAN(Table14[Quantity_Sold]),Table14[[#This Row],[Quantity_Sold]]) -> 12 | R19: =TRIM(Table14[[#This Row],[Product_Category]]) -> Furniture | S19: =PROPER(Table14[[#This Row],[Customer_Type]]) -> New | T19: =IF(ISBLANK(Table14[[#This Row],[Discount]]),MEDIAN(Table14[Discount]),Table14[[#This Row],[Discount]]) -> 0.02
A20: 1426 | B20: 45309 | D20: SOUTH | E20: 25621.81 | F20: 8 | G20: Food | H20: 2968.82 | I20: 4106.06 | J20: Returning | K20: 0.22 | L20: Cash | M20: Online | N20: =IF(ISBLANK(Table14[[#This Row],[Sales_Rep]]),"Unknown",Table14[[#This Row],[Sales_Rep]]) -> Unknown | O20: =PROPER(Table14[[#This Row],[Region]]) -> South | P20: =IF(ISBLANK(Table14[[#This Row],[Sales_Amount]]),MEDIAN(Table14[Sales_Amount]),Table14[[#This Row],[Sales_Amount]]) -> 25621.81 | Q20: =IF(ISBLANK(Table14[[#This Row],[Quantity_Sold]]),MEDIAN(Table14[Quantity_Sold]),Table14[[#This Row],[Quantity_Sold]]) -> 8 | R20: =TRIM(Table14[[#This Row],[Product_Category]]) -> Food | S20: =PROPER(Table14[[#This Row],[Customer_Type]]) -> Returning | T20: =IF(ISBLANK(Table14[[#This Row],[Discount]]),MEDIAN(Table14[Discount]),Table14[[#This Row],[Discount]]) -> 0.22
A21: 1288 | B21: 45369 | C21: David | D21: South | E21: 20271.83 | G21: Electronics | H21: 1329.78 | I21: 1925.15 | J21: returninG | L21: Cash | M21: Online | N21: =IF(ISBLANK(Table14[[#This Row],[Sales_Rep]]),"Unknown",Table14[[#This Row],[Sales_Rep]]) -> David | O21: =PROPER(Table14[[#This Row],[Region]]) -> South | P21: =IF(ISBLANK(Table14[[#This Row],[Sales_Amount]]),MEDIAN(Table14[Sales_Amount]),Table14[[#This Row],[Sales_Amount]]) -> 20271.83 | Q21: =IF(ISBLANK(Table14[[#This Row],[Quantity_Sold]]),MEDIAN(Table14[Quantity_Sold]),Table14[[#This Row],[Quantity_Sold]]) -> 25 | R21: =TRIM(Table14[[#This Row],[Product_Category]]) -> Electronics | S21: =PROPER(Table14[[#This Row],[Customer_Type]]) -> Returning | T21: =IF(ISBLANK(Table14[[#This Row],[Discount]]),MEDIAN(Table14[Discount]),Table14[[#This Row],[Discount]]) -> 0.15
A22: 1337 | B22: 45445 | C22: Bob | D22: East | E22: 7557.82 | G22: Furniture | H22: 915.83 | I22: 1369.17 | J22: Returning | K22: 0.08 | L22: Bank Transfer | M22: Online | N22: =IF(ISBLANK(Table14[[#This Row],[Sales_Rep]]),"Unknown",Table14[[#This Row],[Sales_Rep]]) -> Bob | O22: =PROPER(Table14[[#This Row],[Region]]) -> East | P22: =IF(ISBLANK(Table14[[#This Row],[Sales_Amount]]),MEDIAN(Table14[Sales_Amount]),Table14[[#This Row],[Sales_Amount]]) -> 7557.82 | Q22: =IF(ISBLANK(Table14[[#This Row],[Quantity_Sold]]),MEDIAN(Table14[Quantity_Sold]),Table14[[#This Row],[Quantity_Sold]]) -> 25 | R22: =TRIM(Table14[[#This Row],[Product_Category]]) -> Furniture | S22: =PROPER(Table14[[#This Row],[Customer_Type]]) -> Returning | T22: =IF(ISBLANK(Table14[[#This Row],[Discount]]),MEDIAN(Table14[Discount]),Table14[[#This Row],[Discount]]) -> 0.08
A23: 1319 | B23: 44973 | C23: Eve | D23: East | E23: 112287.09 | F23: 41 | G23: Food | H23: 2844.06 | I23: 3299.65 | J23: New | K23: 0.17 | L23: Cash | M23: Retail | N23: =IF(ISBLANK(Table14[[#This Row],[Sales_Rep]]),"Unknown",Table14[[#This Row],[Sales_Rep]]) -> Eve | O23: =PROPER(Table14[[#This Row],[Region]]) -> East | P23: =IF(ISBLANK(Table14[[#This Row],[Sales_Amount]]),MEDIAN(Table14[Sales_Amount]),Table14[[#This Row],[Sales_Amount]]) -> 112287.09 | Q23: =IF(ISBLANK(Table14[[#This Row],[Quantity_Sold]]),MEDIAN(Table14[Quantity_Sold]),Table14[[#This Row],[Quantity_Sold]]) -> 41 | R23: =TRIM(Table14[[#This Row],[Product_Category]]) -> Food | S23: =PROPER(Table14[[#This Row],[Customer_Type]]) -> New | T23: =IF(ISBLANK(Table14[[#This Row],[Discount]]),MEDIAN(Table14[Discount]),Table14[[#This Row],[Discount]]) -> 0.17
A24: 1205 | B24: 45480 | C24: David | D24: West | E24: 51700.65 | F24: 18 | G24: Furniture | H24: 2763.69 | I24: 3122.02 | J24: New | K24: 0.08 | L24: Cash | M24: Online | N24: =IF(ISBLANK(Table14[[#This Row],[Sales_Rep]]),"Unknown",Table14[[#This Row],[Sales_Rep]]) -> David | O24: =PROPER(Table14[[#This Row],[Region]]) -> West | P24: =IF(ISBLANK(Table14[[#This Row],[Sales_Amount]]),MEDIAN(Table14[Sales_Amount]),Table14[[#This Row],[Sales_Amount]]) -> 51700.65 | Q24: =IF(ISBLANK(Table14[[#This Row],[Quantity_Sold]]),MEDIAN(Table14[Quantity_Sold]),Table14[[#This Row],[Quantity_Sold]]) -> 18 | R24: =TRIM(Table14[[#This Row],[Product_Category]]) -> Furniture | S24: =PROPER(Table14[[#This Row],[Customer_Type]]) -> New | T24: =IF(ISBLANK(Table14[[#This Row],[Discount]]),MEDIAN(Table14[Discount]),Table14[[#This Row],[Discount]]) -> 0.08
A25: 1434 | B25: 45344 | C25: Alice | D25: NORTH | E25: 9329.9 | F25: 6 | G25: Furniture | H25: 1518.93 | I25: 2046.03 | J25: Returning | K25: 0.24 | L25: Bank Transfer | M25: Retail | N25: =IF(ISBLANK(Table14[[#This Row],[Sales_Rep]]),"Unknown",Table14[[#This Row],[Sales_Rep]]) -> Alice | O25: =PROPER(Table14[[#This Row],[Region]]) -> North | P25: =IF(ISBLANK(Table14[[#This Row],[Sales_Amount]]),MEDIAN(Table14[Sales_Amount]),Table14[[#This Row],[Sales_Amount]]) -> 9329.9 | Q25: =IF(ISBLANK(Table14[[#This Row],[Quantity_Sold]]),MEDIAN(Table14[Quantity_Sold]),Table14[[#This Row],[Quantity_Sold]]) -> 6 | R25: =TRIM(Table14[[#This Row],[Product_Category]]) -> Furniture | S25: =PROPER(Table14[[#This Row],[Customer_Type]]) -> Returning | T25: =IF(ISBLANK(Table14[[#This Row],[Discount]]),MEDIAN(Table14[Discount]),Table14[[#This Row],[Discount]]) -> 0.24
A26: 1322 | B26: 45003 | C26: Alice | D26: East | E26: 11086.23 | F26: 3 | G26: Furniture | H26: 2993.59 | I26: 4060.89 | J26: New | K26: 0.09 | L26: Bank Transfer | M26: Online | N26: =IF(ISBLANK(Table14[[#This Row],[Sales_Rep]]),"Unknown",Table14[[#This Row],[Sales_Rep]]) -> Alice | O26: =PROPER(Table14[[#This Row],[Region]]) -> East | P26: =IF(ISBLANK(Table14[[#This Row],[Sales_Amount]]),MEDIAN(Table14[Sales_Amount]),Table14[[#This Row],[Sales_Amount]]) -> 11086.23 | Q26: =IF(ISBLANK(Table14[[#This Row],[Quantity_Sold]]),MEDIAN(Table14[Quantity_Sold]),Table14[[#This Row],[Quantity_Sold]]) -> 3 | R26: =TRIM(Table14[[#This Row],[Product_Category]]) -> Furniture | S26: =PROPER(Table14[[#This Row],[Customer_Type]]) -> New | T26: =IF(ISBLANK(Table14[[#This Row],[Discount]]),MEDIAN(Table14[Discount]),Table14[[#This Row],[Discount]]) -> 0.09
A27: 1165 | B27: 45143 | C27: Charlie | D27: South | E27: 2639.43 | F27: 18 | G27: Furniture | H27: 151.27 | I27: 203.66 | J27: new | K27: 0.28 | L27: Bank Transfer | M27: Retail | N27: =IF(ISBLANK(Table14[[#This Row],[Sales_Rep]]),"Unknown",Table14[[#This Row],[Sales_Rep]]) -> Charlie | O27: =PROPER(Table14[[#This Row],[Region]]) -> South | P27: =IF(ISBLANK(Table14[[#This Row],[Sales_Amount]]),MEDIAN(Table14[Sales_Amount]),Table14[[#This Row],[Sales_Amount]]) -> 2639.43 | Q27: =IF(ISBLANK(Table14[[#This Row],[Quantity_Sold]]),MEDIAN(Table14[Quantity_Sold]),Table14[[#This Row],[Quantity_Sold]]) -> 18 | R27: =TRIM(Table14[[#This Row],[Product_Category]]) -> Furniture | S27: =PROPER(Table14[[#This Row],[Customer_Type]]) -> New | T27: =IF(ISBLANK(Table14[[#This Row],[Discount]]),MEDIAN(Table14[Discount]),Table14[[#This Row],[Discount]]) -> 0.28
A28: 1154 | B28: 45618 | C28: Charlie | D28: West | E28: 26058.24 | F28: 24 | G28: Food | H28: 952.7 | I28: 1392 | J28: New | K28: 0.22 | L28: Bank Transfer | M28: Online | N28: =IF(ISBLANK(Table14[[#This Row],[Sales_Rep]]),"Unknown",Table14[[#This Row],[Sales_Rep]]) -> Charlie | O28: =PROPER(Table14[[#This Row],[Region]]) -> West | P28: =IF(ISBLANK(Table14[[#This Row],[Sales_Amount]]),MEDIAN(Table14[Sales_Amount]),Table14[[#This Row],[Sales_Amount]]) -> 26058.24 | Q28: =IF(ISBLANK(Table14[[#This Row],[Quantity_Sold]]),MEDIAN(Table14[Quantity_Sold]),Table14[[#This Row],[Quantity_Sold]]) -> 24 | R28: =TRIM(Table14[[#This Row],[Product_Category]]) -> Food | S28: =PROPER(Table14[[#This Row],[Customer_Type]]) -> New | T28: =IF(ISBLANK(Table14[[#This Row],[Discount]]),MEDIAN(Table14[Discount]),Table14[[#This Row],[Discount]]) -> 0.22
A29: 1103 | B29: 44933 | D29: East | E29: 16454.74 | F29: 6 | G29: Electronics | H29: 2449.66 | I29: 3515.97 | J29: New | K29: 0.22 | L29: Cash | M29: Online | N29: =IF(ISBLANK(Table14[[#This Row],[Sales_Rep]]),"Unknown",Table14[[#This Row],[Sales_Rep]]) -> Unknown | O29: =PROPER(Table14[[#This Row],[Region]]) -> East | P29: =IF(ISBLANK(Table14[[#This Row],[Sales_Amount]]),MEDIAN(Table14[Sales_Amount]),Table14[[#This Row],[Sales_Amount]]) -> 16454.74 | Q29: =IF(ISBLANK(Table14[[#This Row],[Quantity_Sold]]),MEDIAN(Table14[Quantity_Sold]),Table14[[#This Row],[Quantity_Sold]]) -> 6 | R29: =TRIM(Table14[[#This Row],[Product_Category]]) -> Electronics | S29: =PROPER(Table14[[#This Row],[Customer_Type]]) -> New | T29: =IF(ISBLANK(Table14[[#This Row],[Discount]]),MEDIAN(Table14[Discount]),Table14[[#This Row],[Discount]]) -> 0.22
A30: 1003 | B30: 45142 | C30: David | D30: West | E30: 2136.41 | F30: 13 | G30: Electronics | H30: 149.55 | I30: 193.34 | J30: new | K30: 0.15 | L30: Cash | M30: Online | N30: =IF(ISBLANK(Table14[[#This Row],[Sales_Rep]]),"Unknown",Table14[[#This Row],[Sales_Rep]]) -> David | O30: =PROPER(Table14[[#This Row],[Region]]) -> West | P30: =IF(ISBLANK(Table14[[#This Row],[Sales_Amount]]),MEDIAN(Table14[Sales_Amount]),Table14[[#This Row],[Sales_Amount]]) -> 2136.41 | Q30: =IF(ISBLANK(Table14[[#This Row],[Quantity_Sold]]),MEDIAN(Table14[Quantity_Sold]),Table14[[#This Row],[Quantity_Sold]]) -> 13 | R30: =TRIM(Table14[[#This Row],[Product_Category]]) -> Electronics | S30: =PROPER(Table14[[#This Row],[Customer_Type]]) -> New | T30: =IF(ISBLANK(Table14[[#This Row],[Discount]]),MEDIAN(Table14[Discount]),Table14[[#This Row],[Discount]]) -> 0.15
A31: 1067 | B31: 45462 | C31: David | D31: North | E31: 264002.31 | F31: 39 | G31: Clothing | H31: 4707.48 | I31: 6769.29 | J31: Returning | K31: 0 | L31: Credit Card | M31: Retail | N31: =IF(ISBLANK(Table14[[#This Row],[Sales_Rep]]),"Unknown",Table14[[#This Row],[Sales_Rep]]) -> David | O31: =PROPER(Table14[[#This Row],[Region]]) -> North | P31: =IF(ISBLANK(Table14[[#This Row],[Sales_Amount]]),MEDIAN(Table14[Sales_Amount]),Table14[[#This Row],[Sales_Amount]]) -> 264002.31 | Q31: =IF(ISBLANK(Table14[[#This Row],[Quantity_Sold]]),MEDIAN(Table14[Quantity_Sold]),Table14[[#This Row],[Quantity_Sold]]) -> 39 | R31: =TRIM(Table14[[#This Row],[Product_Category]]) -> Clothing | S31: =PROPER(Table14[[#This Row],[Customer_Type]]) -> Returning | T31: =IF(ISBLANK(Table14[[#This Row],[Discount]]),MEDIAN(Table14[Discount]),Table14[[#This Row],[Discount]]) -> 0
A32: 1332 | B32: 45316 | C32: Charlie | D32: East | E32: 48686.3 | F32: 18 | G32: Clothing | H32: 2779.59 | I32: 3298.53 | J32: Returning | K32: 0.18 | L32: Cash | M32: Retail | N32: =IF(ISBLANK(Table14[[#This Row],[Sales_Rep]]),"Unknown",Table14[[#This Row],[Sales_Rep]]) -> Charlie | O32: =PROPER(Table14[[#This Row],[Region]]) -> East | P32: =IF(ISBLANK(Table14[[#This Row],[Sales_Amount]]),MEDIAN(Table14[Sales_Amount]),Table14[[#This Row],[Sales_Amount]]) -> 48686.3 | Q32: =IF(ISBLANK(Table14[[#This Row],[Quantity_Sold]]),MEDIAN(Table14[Quantity_Sold]),Table14[[#This Row],[Quantity_Sold]]) -> 18 | R32: =TRIM(Table14[[#This Row],[Product_Category]]) -> Clothing | S32: =PROPER(Table14[[#This Row],[Customer_Type]]) -> Returning | T32: =IF(ISBLANK(Table14[[#This Row],[Discount]]),MEDIAN(Table14[Discount]),Table14[[#This Row],[Discount]]) -> 0.18
A33: 1308 | B33: 45051 | C33: David | D33: SOUTH | E33: 6882.52 | F33: 7 | G33: Furniture | H33: 1187.82 | I33: 1365.58 | J33: New | K33: 0.28 | L33: Bank Transfer | M33: Retail | N33: =IF(ISBLANK(Table14[[#This Row],[Sales_Rep]]),"Unknown",Table14[[#This Row],[Sales_Rep]]) -> David | O33: =PROPER(Table14[[#This Row],[Region]]) -> South | P33: =IF(ISBLANK(Table14[[#This Row],[Sales_Amount]]),MEDIAN(Table14[Sales_Amount]),Table14[[#This Row],[Sales_Amount]]) -> 6882.52 | Q33: =IF(ISBLANK(Table14[[#This Row],[Quantity_Sold]]),MEDIAN(Table14[Quantity_Sold]),Table14[[#This Row],[Quantity_Sold]]) -> 7 | R33: =TRIM(Table14[[#This Row],[Product_Category]]) -> Furniture | S33: =PROPER(Table14[[#This Row],[Customer_Type]]) -> New | T33: =IF(ISBLANK(Table14[[#This Row],[Discount]]),MEDIAN(Table14[Discount]),Table14[[#This Row],[Discount]]) -> 0.28
A34: 1421 | B34: 45220 | C34: David | D34: East | E34: 117576.01 | F34: 37 | G34: Furniture | H34: 2209.4 | I34: 3177.73 | J34: Returning | K34: 0 | L34: Bank Transfer | M34: Online | N34: =IF(ISBLANK(Table14[[#This Row],[Sales_Rep]]),"Unknown",Table14[[#This Row],[Sales_Rep]]) -> David | O34: =PROPER(Table14[[#This Row],[Region]]) -> East | P34: =IF(ISBLANK(Table14[[#This Row],[Sales_Amount]]),MEDIAN(Table14[Sales_Amount]),Table14[[#This Row],[Sales_Amount]]) -> 117576.01 | Q34: =IF(ISBLANK(Table14[[#This Row],[Quantity_Sold]]),MEDIAN(Table14[Quantity_Sold]),Table14[[#This Row],[Quantity_Sold]]) -> 37 | R34: =TRIM(Table14[[#This Row],[Product_Category]]) -> Furniture | S34: =PROPER(Table14[[#This Row],[Customer_Type]]) -> Returning | T34: =IF(ISBLANK(Table14[[#This Row],[Discount]]),MEDIAN(Table14[Discount]),Table14[[#This Row],[Discount]]) -> 0
A35: 1088 | B35: 45100 | C35: Alice | D35: west | E35: 3588.45 | F35: 4 | G35: Food | H35: 905.02 | I35: 1196.15 | J35: New | K35: 0.25 | L35: Bank Transfer | M35: Retail | N35: =IF(ISBLANK(Table14[[#This Row],[Sales_Rep]]),"Unknown",Table14[[#This Row],[Sales_Rep]]) -> Alice | O35: =PROPER(Table14[[#This Row],[Region]]) -> West | P35: =IF(ISBLANK(Table14[[#This Row],[Sales_Amount]]),MEDIAN(Table14[Sales_Amount]),Table14[[#This Row],[Sales_Amount]]) -> 3588.45 | Q35: =IF(ISBLANK(Table14[[#This Row],[Quantity_Sold]]),MEDIAN(Table14[Quantity_Sold]),Table14[[#This Row],[Quantity_Sold]]) -> 4 | R35: =TRIM(Table14[[#This Row],[Product_Category]]) -> Food | S35: =PROPER(Table14[[#This Row],[Customer_Type]]) -> New | T35: =IF(ISBLANK(Table14[[#This Row],[Discount]]),MEDIAN(Table14[Discount]),Table14[[#This Row],[Discount]]) -> 0.25
A36: 1166 | B36: 45235 | C36: Charlie | D36: East | E36: 2399.28 | F36: 1 | G36: Clothing | H36: 1991.33 | I36: 2856.29 | J36: new | K36: 0.16 | L36: Bank Transfer | M36: Retail | N36: =IF(ISBLANK(Table14[[#This Row],[Sales_Rep]]),"Unknown",Table14[[#This Row],[Sales_Rep]]) -> Charlie | O36: =PROPER(Table14[[#This Row],[Region]]) -> East | P36: =IF(ISBLANK(Table14[[#This Row],[Sales_Amount]]),MEDIAN(Table14[Sales_Amount]),Table14[[#This Row],[Sales_Amount]]) -> 2399.28 | Q36: =IF(ISBLANK(Table14[[#This Row],[Quantity_Sold]]),MEDIAN(Table14[Quantity_Sold]),Table14[[#This Row],[Quantity_Sold]]) -> 1 | R36: =TRIM(Table14[[#This Row],[Product_Category]]) -> Clothing | S36: =PROPER(Table14[[#This Row],[Customer_Type]]) -> New | T36: =IF(ISBLANK(Table14[[#This Row],[Discount]]),MEDIAN(Table14[Discount]),Table14[[#This Row],[Discount]]) -> 0.16
A37: 1362 | B37: 45068 | C37: Eve | D37: South | E37: 9432.76 | F37: 5 | G37: Furniture | H37: 1527.92 | I37: 2006.97 | J37: New | L37: Cash | M37: Retail | N37: =IF(ISBLANK(Table14[[#This Row],[Sales_Rep]]),"Unknown",Table14[[#This Row],[Sales_Rep]]) -> Eve | O37: =PROPER(Table14[[#This Row],[Region]]) -> South | P37: =IF(ISBLANK(Table14[[#This Row],[Sales_Amount]]),MEDIAN(Table14[Sales_Amount]),Table14[[#This Row],[Sales_Amount]]) -> 9432.76 | Q37: =IF(ISBLANK(Table14[[#This Row],[Quantity_Sold]]),MEDIAN(Table14[Quantity_Sold]),Table14[[#This Row],[Quantity_Sold]]) -> 5 | R37: =TRIM(Table14[[#This Row],[Product_Category]]) -> Furniture | S37: =PROPER(Table14[[#This Row],[Customer_Type]]) -> New | T37: =IF(ISBLANK(Table14[[#This Row],[Discount]]),MEDIAN(Table14[Discount]),Table14[[#This Row],[Discount]]) -> 0.15
A38: 1311 | B38: 45396 | C38: Charlie | D38: South | F38: 39 | G38: Clothing | H38: 3976.45 | I38: 5201.72 | J38: New | K38: 0.18 | L38: Cash | M38: Online | N38: =IF(ISBLANK(Table14[[#This Row],[Sales_Rep]]),"Unknown",Table14[[#This Row],[Sales_Rep]]) -> Charlie | O38: =PROPER(Table14[[#This Row],[Region]]) -> South | P38: =IF(ISBLANK(Table14[[#This Row],[Sales_Amount]]),MEDIAN(Table14[Sales_Amount]),Table14[[#This Row],[Sales_Amount]]) -> 50770.89 | Q38: =IF(ISBLANK(Table14[[#This Row],[Quantity_Sold]]),MEDIAN(Table14[Quantity_Sold]),Table14[[#This Row],[Quantity_Sold]]) -> 39 | R38: =TRIM(Table14[[#This Row],[Product_Category]]) -> Clothing | S38: =PROPER(Table14[[#This Row],[Customer_Type]]) -> New | T38: =IF(ISBLANK(Table14[[#This Row],[Discount]]),MEDIAN(Table14[Discount]),Table14[[#This Row],[Discount]]) -> 0.18
A39: 1038 | B39: 45406 | C39: Eve | D39: West | F39: 24 | G39: Electronics | H39: 2282.47 | I39: 2558.37 | J39: Returning | K39: 0.02 | L39: Cash | M39: Retail | N39: =IF(ISBLANK(Table14[[#This Row],[Sales_Rep]]),"Unknown",Table14[[#This Row],[Sales_Rep]]) -> Eve | O39: =PROPER(Table14[[#This Row],[Region]]) -> West | P39: =IF(ISBLANK(Table14[[#This Row],[Sales_Amount]]),MEDIAN(Table14[Sales_Amount]),Table14[[#This Row],[Sales_Amount]]) -> 50770.89 | Q39: =IF(ISBLANK(Table14[[#This Row],[Quantity_Sold]]),MEDIAN(Table14[Quantity_Sold]),Table14[[#This Row],[Quantity_Sold]]) -> 24 | R39: =TRIM(Table14[[#This Row],[Product_Category]]) -> Electronics | S39: =PROPER(Table14[[#This Row],[Customer_Type]]) -> Returning | T39: =IF(ISBLANK(Table14[[#This Row],[Discount]]),MEDIAN(Table14[Discount]),Table14[[#This Row],[Discount]]) -> 0.02
A40: 1001 | B40: 45614 | C40: Alice | D40: West | E40: 56953.67 | F40: 19 | G40: Electronics | H40: 3366.81 | I40: 4163.28 | J40: New | K40: 0.28 | L40: Credit Card | M40: Retail | N40: =IF(ISBLANK(Table14[[#This Row],[Sales_Rep]]),"Unknown",Table14[[#This Row],[Sales_Rep]]) -> Alice | O40: =PROPER(Table14[[#This Row],[Region]]) -> West | P40: =IF(ISBLANK(Table14[[#This Row],[Sales_Amount]]),MEDIAN(Table14[Sales_Amount]),Table14[[#This Row],[Sales_Amount]]) -> 56953.67 | Q40: =IF(ISBLANK(Table14[[#This Row],[Quantity_Sold]]),MEDIAN(Table14[Quantity_Sold]),Table14[[#This Row],[Quantity_Sold]]) -> 19 | R40: =TRIM(Table14[[#This Row],[Product_Category]]) -> Electronics | S40: =PROPER(Table14[[#This Row],[Customer_Type]]) -> New | T40: =IF(ISBLANK(Table14[[#This Row],[Discount]]),MEDIAN(Table14[Discount]),Table14[[#This Row],[Discount]]) -> 0.28
A41: 1184 | B41: 44941 | C41: Bob | D41: South | E41: 164921.02 | F41: 49 | G41: Furniture | H41: 3039.91 | I41: 3619.07 | J41: New | K41: 0.07 | L41: Bank Transfer | M41: Retail | N41: =IF(ISBLANK(Table14[[#This Row],[Sales_Rep]]),"Unknown",Table14[[#This Row],[Sales_Rep]]) -> Bob | O41: =PROPER(Table14[[#This Row],[Region]]) -> South | P41: =IF(ISBLANK(Table14[[#This Row],[Sales_Amount]]),MEDIAN(Table14[Sales_Amount]),Table14[[#This Row],[Sales_Amount]]) -> 164921.02 | Q41: =IF(ISBLANK(Table14[[#This Row],[Quantity_Sold]]),MEDIAN(Table14[Quantity_Sold]),Table14[[#This Row],[Quantity_Sold]]) -> 49 | R41: =TRIM(Table14[[#This Row],[Product_Category]]) -> Furniture | S41: =PROPER(Table14[[#This Row],[Customer_Type]]) -> New | T41: =IF(ISBLANK(Table14[[#This Row],[Discount]]),MEDIAN(Table14[Discount]),Table14[[#This Row],[Discount]]) -> 0.07
A42: 1147 | B42: 44969 | D42: East | E42: 20392.21 | F42: 14 | G42: Food | H42: 1739.24 | I42: 2051.53 | J42: Returning | K42: 0.29 | L42: Bank Transfer | M42: Retail | N42: =IF(ISBLANK(Table14[[#This Row],[Sales_Rep]]),"Unknown",Table14[[#This Row],[Sales_Rep]]) -> Unknown | O42: =PROPER(Table14[[#This Row],[Region]]) -> East | P42: =IF(ISBLANK(Table14[[#This Row],[Sales_Amount]]),MEDIAN(Table14[Sales_Amount]),Table14[[#This Row],[Sales_Amount]]) -> 20392.21 | Q42: =IF(ISBLANK(Table14[[#This Row],[Quantity_Sold]]),MEDIAN(Table14[Quantity_Sold]),Table14[[#This Row],[Quantity_Sold]]) -> 14 | R42: =TRIM(Table14[[#This Row],[Product_Category]]) -> Food | S42: =PROPER(Table14[[#This Row],[Customer_Type]]) -> Returning | T42: =IF(ISBLANK(Table14[[#This Row],[Discount]]),MEDIAN(Table14[Discount]),Table14[[#This Row],[Discount]]) -> 0.29
A43: 1252 | B43: 45471 | D43: West | E43: 16437.78 | F43: 20 | G43: Clothing | H43: 770.05 | I43: 874.35 | J43: New | K43: 0.06 | L43: Bank Transfer | M43: Retail | N43: =IF(ISBLANK(Table14[[#This Row],[Sales_Rep]]),"Unknown",Table14[[#This Row],[Sales_Rep]]) -> Unknown | O43: =PROPER(Table14[[#This Row],[Region]]) -> West | P43: =IF(ISBLANK(Table14[[#This Row],[Sales_Amount]]),MEDIAN(Table14[Sales_Amount]),Table14[[#This Row],[Sales_Amount]]) -> 16437.78 | Q43: =IF(ISBLANK(Table14[[#This Row],[Quantity_Sold]]),MEDIAN(Table14[Quantity_Sold]),Table14[[#This Row],[Quantity_Sold]]) -> 20 | R43: =TRIM(Table14[[#This Row],[Product_Category]]) -> Clothing | S43: =PROPER(Table14[[#This Row],[Customer_Type]]) -> New | T43: =IF(ISBLANK(Table14[[#This Row],[Discount]]),MEDIAN(Table14[Discount]),Table14[[#This Row],[Discount]]) -> 0.06
A44: 1032 | B44: 45220 | C44: David | D44: West | E44: 24970.36 | F44: 11 | G44: Electronics | H44: 1844.37 | I44: 2316.36 | J44: Returning | K44: 0.02 | L44: Bank Transfer | M44: Online | N44: =IF(ISBLANK(Table14[[#This Row],[Sales_Rep]]),"Unknown",Table14[[#This Row],[Sales_Rep]]) -> David | O44: =PROPER(Table14[[#This Row],[Region]]) -> West | P44: =IF(ISBLANK(Table14[[#This Row],[Sales_Amount]]),MEDIAN(Table14[Sales_Amount]),Table14[[#This Row],[Sales_Amount]]) -> 24970.36 | Q44: =IF(ISBLANK(Table14[[#This Row],[Quantity_Sold]]),MEDIAN(Table14[Quantity_Sold]),Table14[[#This Row],[Quantity_Sold]]) -> 11 | R44: =TRIM(Table14[[#This Row],[Product_Category]]) -> Electronics | S44: =PROPER(Table14[[#This Row],[Customer_Type]]) -> Returning | T44: =IF(ISBLANK(Table14[[#This Row],[Discount]]),MEDIAN(Table14[Discount]),Table14[[#This Row],[Discount]]) -> 0.02
A45: 1402 | B45: 45610 | C45: Bob | D45: East | E45: 31145.14 | F45: 44 | G45: Clothing | H45: 638.38 | I45: 722.29 | J45: Returning | K45: 0.02 | L45: Credit Card | M45: Online | N45: =IF(ISBLANK(Table14[[#This Row],[Sales_Rep]]),"Unknown",Table14[[#This Row],[Sales_Rep]]) -> Bob | O45: =PROPER(Table14[[#This Row],[Region]]) -> East | P45: =IF(ISBLANK(Table14[[#This Row],[Sales_Amount]]),MEDIAN(Table14[Sales_Amount]),Table14[[#This Row],[Sales_Amount]]) -> 31145.14 | Q45: =IF(ISBLANK(Table14[[#This Row],[Quantity_Sold]]),MEDIAN(Table14[Quantity_Sold]),Table14[[#This Row],[Quantity_Sold]]) -> 44 | R45: =TRIM(Table14[[#This Row],[Product_Category]]) -> Clothing | S45: =PROPER(Table14[[#This Row],[Customer_Type]]) -> Returning | T45: =IF(ISBLANK(Table14[[#This Row],[Discount]]),MEDIAN(Table14[Discount]),Table14[[#This Row],[Discount]]) -> 0.02
A46: 1036 | B46: 45012 | C46: Bob | D46: East | E46: 7451.08 | F46: 7 | G46: Furniture | H46: 770.86 | I46: 1064.44 | J46: returning | K46: 0 | L46: Bank Transfer | M46: Online | N46: =IF(ISBLANK(Table14[[#This Row],[Sales_Rep]]),"Unknown",Table14[[#This Row],[Sales_Rep]]) -> Bob | O46: =PROPER(Table14[[#This Row],[Region]]) -> East | P46: =IF(ISBLANK(Table14[[#This Row],[Sales_Amount]]),MEDIAN(Table14[Sales_Amount]),Table14[[#This Row],[Sales_Amount]]) -> 7451.08 | Q46: =IF(ISBLANK(Table14[[#This Row],[Quantity_Sold]]),MEDIAN(Table14[Quantity_Sold]),Table14[[#This Row],[Quantity_Sold]]) -> 7 | R46: =TRIM(Table14[[#This Row],[Product_Category]]) -> Furniture | S46: =PROPER(Table14[[#This Row],[Customer_Type]]) -> Returning | T46: =IF(ISBLANK(Table14[[#This Row],[Discount]]),MEDIAN(Table14[Discount]),Table14[[#This Row],[Discount]]) -> 0
A47: 1323 | B47: 45427 | C47: Alice | D47: South | E47: 168954.62 | F47: 36 | G47: Furniture | H47: 4420.25 | I47: 5866.48 | J47: Returning | K47: 0.2 | L47: Cash | M47: Retail | N47: =IF(ISBLANK(Table14[[#This Row],[Sales_Rep]]),"Unknown",Table14[[#This Row],[Sales_Rep]]) -> Alice | O47: =PROPER(Table14[[#This Row],[Region]]) -> South | P47: =IF(ISBLANK(Table14[[#This Row],[Sales_Amount]]),MEDIAN(Table14[Sales_Amount]),Table14[[#This Row],[Sales_Amount]]) -> 168954.62 | Q47: =IF(ISBLANK(Table14[[#This Row],[Quantity_Sold]]),MEDIAN(Table14[Quantity_Sold]),Table14[[#This Row],[Quantity_Sold]]) -> 36 | R47: =TRIM(Table14[[#This Row],[Product_Category]]) -> Furniture | S47: =PROPER(Table14[[#This Row],[Customer_Type]]) -> Returning | T47: =IF(ISBLANK(Table14[[#This Row],[Discount]]),MEDIAN(Table14[Discount]),Table14[[#This Row],[Discount]]) -> 0.2
A48: 1371 | B48: 45468 | C48: Bob | D48: South | E48: 69836.41 | F48: 25 | G48: Furniture | H48: 2779.29 | I48: 3365.61 | J48: Returning | K48: 0.17 | L48: Bank Transfer | M48: Retail | N48: =IF(ISBLANK(Table14[[#This Row],[Sales_Rep]]),"Unknown",Table14[[#This Row],[Sales_Rep]]) -> Bob | O48: =PROPER(Table14[[#This Row],[Region]]) -> South | P48: =IF(ISBLANK(Table14[[#This Row],[Sales_Amount]]),MEDIAN(Table14[Sales_Amount]),Table14[[#This Row],[Sales_Amount]]) -> 69836.41 | Q48: =IF(ISBLANK(Table14[[#This Row],[Quantity_Sold]]),MEDIAN(Table14[Quantity_Sold]),Table14[[#This Row],[Quantity_Sold]]) -> 25 | R48: =TRIM(Table14[[#This Row],[Product_Category]]) -> Furniture | S48: =PROPER(Table14[[#This Row],[Customer_Type]]) -> Returning | T48: =IF(ISBLANK(Table14[[#This Row],[Discount]]),MEDIAN(Table14[Discount]),Table14[[#This Row],[Discount]]) -> 0.17
A49: 1116 | B49: 45378 | C49: Eve | D49: North | E49: 108442.32 | F49: 38 | G49: Electronics | H49: 3097.56 | I49: 3909.24 | J49: New | K49: 0.27 | L49: Cash | M49: Retail | N49: =IF(ISBLANK(Table14[[#This Row],[Sales_Rep]]),"Unknown",Table14[[#This Row],[Sales_Rep]]) -> Eve | O49: =PROPER(Table14[[#This Row],[Region]]) -> North | P49: =IF(ISBLANK(Table14[[#This Row],[Sales_Amount]]),MEDIAN(Table14[Sales_Amount]),Table14[[#This Row],[Sales_Amount]]) -> 108442.32 | Q49: =IF(ISBLANK(Table14[[#This Row],[Quantity_Sold]]),MEDIAN(Table14[Quantity_Sold]),Table14[[#This Row],[Quantity_Sold]]) -> 38 | R49: =TRIM(Table14[[#This Row],[Product_Category]]) -> Electronics | S49: =PROPER(Table14[[#This Row],[Customer_Type]]) -> New | T49: =IF(ISBLANK(Table14[[#This Row],[Discount]]),MEDIAN(Table14[Discount]),Table14[[#This Row],[Discount]]) -> 0.27
A50: 1260 | B50: 45493 | C50: Bob | D50: East | E50: 57719.28 | F50: 39 | G50: Furniture | H50: 1448.19 | I50: 2055.53 | J50: new | K50: 0.28 | L50: Bank Transfer | M50: Online | N50: =IF(ISBLANK(Table14[[#This Row],[Sales_Rep]]),"Unknown",Table14[[#This Row],[Sales_Rep]]) -> Bob | O50: =PROPER(Table14[[#This Row],[Region]]) -> East | P50: =IF(ISBLANK(Table14[[#This Row],[Sales_Amount]]),MEDIAN(Table14[Sales_Amount]),Table14[[#This Row],[Sales_Amount]]) -> 57719.28 | Q50: =IF(ISBLANK(Table14[[#This Row],[Quantity_Sold]]),MEDIAN(Table14[Quantity_Sold]),Table14[[#This Row],[Quantity_Sold]]) -> 39 | R50: =TRIM(Table14[[#This Row],[Product_Category]]) -> Furniture | S50: =PROPER(Table14[[#This Row],[Customer_Type]]) -> New | T50: =IF(ISBLANK(Table14[[#This Row],[Discount]]),MEDIAN(Table14[Discount]),Table14[[#This Row],[Discount]]) -> 0.28
A51: 1119 | B51: 45433 | C51: David | D51: South | F51: 19 | G51: Electronics | H51: 3733.7 | I51: 5453.97 | J51: New | K51: 0.2 | L51: Bank Transfer | M51: Online | N51: =IF(ISBLANK(Table14[[#This Row],[Sales_Rep]]),"Unknown",Table14[[#This Row],[Sales_Rep]]) -> David | O51: =PROPER(Table14[[#This Row],[Region]]) -> South | P51: =IF(ISBLANK(Table14[[#This Row],[Sales_Amount]]),MEDIAN(Table14[Sales_Amount]),Table14[[#This Row],[Sales_Amount]]) -> 50770.89 | Q51: =IF(ISBLANK(Table14[[#This Row],[Quantity_Sold]]),MEDIAN(Table14[Quantity_Sold]),Table14[[#This Row],[Quantity_Sold]]) -> 19 | R51: =TRIM(Table14[[#This Row],[Product_Category]]) -> Electronics | S51: =PROPER(Table14[[#This Row],[Customer_Type]]) -> New | T51: =IF(ISBLANK(Table14[[#This Row],[Discount]]),MEDIAN(Table14[Discount]),Table14[[#This Row],[Discount]]) -> 0.2
A52: 1226 | B52: 45530 | C52: David | D52: SOUTH | E52: 10598.2 | F52: 48 | G52: Clothing | H52: 233.02 | I52: 302.46 | J52: Returning | K52: 0.27 | L52: Cash | M52: Retail | N52: =IF(ISBLANK(Table14[[#This Row],[Sales_Rep]]),"Unknown",Table14[[#This Row],[Sales_Rep]]) -> David | O52: =PROPER(Table14[[#This Row],[Region]]) -> South | P52: =IF(ISBLANK(Table14[[#This Row],[Sales_Amount]]),MEDIAN(Table14[Sales_Amount]),Table14[[#This Row],[Sales_Amount]]) -> 10598.2 | Q52: =IF(ISBLANK(Table14[[#This Row],[Quantity_Sold]]),MEDIAN(Table14[Quantity_Sold]),Table14[[#This Row],[Quantity_Sold]]) -> 48 | R52: =TRIM(Table14[[#This Row],[Product_Category]]) -> Clothing | S52: =PROPER(Table14[[#This Row],[Customer_Type]]) -> Returning | T52: =IF(ISBLANK(Table14[[#This Row],[Discount]]),MEDIAN(Table14[Discount]),Table14[[#This Row],[Discount]]) -> 0.27
A53: 1106 | B53: 45069 | C53: David | D53: North | E53: 48260.93 | F53: 11 | G53: Food | H53: 4331.17 | I53: 5416.49 | J53: Returning | K53: 0.19 | L53: Credit Card | M53: Retail | N53: =IF(ISBLANK(Table14[[#This Row],[Sales_Rep]]),"Unknown",Table14[[#This Row],[Sales_Rep]]) -> David | O53: =PROPER(Table14[[#This Row],[Region]]) -> North | P53: =IF(ISBLANK(Table14[[#This Row],[Sales_Amount]]),MEDIAN(Table14[Sales_Amount]),Table14[[#This Row],[Sales_Amount]]) -> 48260.93 | Q53: =IF(ISBLANK(Table14[[#This Row],[Quantity_Sold]]),MEDIAN(Table14[Quantity_Sold]),Table14[[#This Row],[Quantity_Sold]]) -> 11 | R53: =TRIM(Table14[[#This Row],[Product_Category]]) -> Food | S53: =PROPER(Table14[[#This Row],[Customer_Type]]) -> Returning | T53: =IF(ISBLANK(Table14[[#This Row],[Discount]]),MEDIAN(Table14[Discount]),Table14[[#This Row],[Discount]]) -> 0.19
A54: 1294 | B54: 45446 | C54: David | D54: South | E54: 118546.45 | F54: 40 | G54: Furniture | H54: 2685.46 | I54: 3751.47 | J54: New | K54: 0.21 | L54: Bank Transfer | M54: Online | N54: =IF(ISBLANK(Table14[[#This Row],[Sales_Rep]]),"Unknown",Table14[[#This Row],[Sales_Rep]]) -> David | O54: =PROPER(Table14[[#This Row],[Region]]) -> South | P54: =IF(ISBLANK(Table14[[#This Row],[Sales_Amount]]),MEDIAN(Table14[Sales_Amount]),Table14[[#This Row],[Sales_Amount]]) -> 118546.45 | Q54: =IF(ISBLANK(Table14[[#This Row],[Quantity_Sold]]),MEDIAN(Table14[Quantity_Sold]),Table14[[#This Row],[Quantity_Sold]]) -> 40 | R54: =TRIM(Table14[[#This Row],[Product_Category]]) -> Furniture | S54: =PROPER(Table14[[#This Row],[Customer_Type]]) -> New | T54: =IF(ISBLANK(Table14[[#This Row],[Discount]]),MEDIAN(Table14[Discount]),Table14[[#This Row],[Discount]]) -> 0.21
A55: 1271 | B55: 45330 | C55: Eve | D55: North | E55: 94771.99 | F55: 39 | G55: Clothing | H55: 2611.47 | I55: 3115.45 | J55: New | K55: 0.22 | L55: Cash | M55: Retail | N55: =IF(ISBLANK(Table14[[#This Row],[Sales_Rep]]),"Unknown",Table14[[#This Row],[Sales_Rep]]) -> Eve | O55: =PROPER(Table14[[#This Row],[Region]]) -> North | P55: =IF(ISBLANK(Table14[[#This Row],[Sales_Amount]]),MEDIAN(Table14[Sales_Amount]),Table14[[#This Row],[Sales_Amount]]) -> 94771.99 | Q55: =IF(ISBLANK(Table14[[#This Row],[Quantity_Sold]]),MEDIAN(Table14[Quantity_Sold]),Table14[[#This Row],[Quantity_Sold]]) -> 39 | R55: =TRIM(Table14[[#This Row],[Product_Category]]) -> Clothing | S55: =PROPER(Table14[[#This Row],[Customer_Type]]) -> New | T55: =IF(ISBLANK(Table14[[#This Row],[Discount]]),MEDIAN(Table14[Discount]),Table14[[#This Row],[Discount]]) -> 0.22
A56: 1272 | B56: 44961 | C56: Charlie | D56: South | E56: 143250.5 | F56: 33 | G56: Furniture | H56: 4294.12 | I56: 5293.81 | J56: Returning | K56: 0.18 | L56: Bank Transfer | M56: Online | N56: =IF(ISBLANK(Table14[[#This Row],[Sales_Rep]]),"Unknown",Table14[[#This Row],[Sales_Rep]]) -> Charlie | O56: =PROPER(Table14[[#This Row],[Region]]) -> South | P56: =IF(ISBLANK(Table14[[#This Row],[Sales_Amount]]),MEDIAN(Table14[Sales_Amount]),Table14[[#This Row],[Sales_Amount]]) -> 143250.5 | Q56: =IF(ISBLANK(Table14[[#This Row],[Quantity_Sold]]),MEDIAN(Table14[Quantity_Sold]),Table14[[#This Row],[Quantity_Sold]]) -> 33 | R56: =TRIM(Table14[[#This Row],[Product_Category]]) -> Furniture | S56: =PROPER(Table14[[#This Row],[Customer_Type]]) -> Returning | T56: =IF(ISBLANK(Table14[[#This Row],[Discount]]),MEDIAN(Table14[Discount]),Table14[[#This Row],[Discount]]) -> 0.18
A57: 1165 | B57: 45136 | D57: South | E57: 105479.39 | F57: 23 | G57: Furniture | H57: 4839.78 | I57: 6034.29 | J57: New | K57: 0.24 | L57: Bank Transfer | M57: Retail | N57: =IF(ISBLANK(Table14[[#This Row],[Sales_Rep]]),"Unknown",Table14[[#This Row],[Sales_Rep]]) -> Unknown | O57: =PROPER(Table14[[#This Row],[Region]]) -> South | P57: =IF(ISBLANK(Table14[[#This Row],[Sales_Amount]]),MEDIAN(Table14[Sales_Amount]),Table14[[#This Row],[Sales_Amount]]) -> 105479.39 | Q57: =IF(ISBLANK(Table14[[#This Row],[Quantity_Sold]]),MEDIAN(Table14[Quantity_Sold]),Table14[[#This Row],[Quantity_Sold]]) -> 23 | R57: =TRIM(Table14[[#This Row],[Product_Category]]) -> Furniture | S57: =PROPER(Table14[[#This Row],[Customer_Type]]) -> New | T57: =IF(ISBLANK(Table14[[#This Row],[Discount]]),MEDIAN(Table14[Discount]),Table14[[#This Row],[Discount]]) -> 0.24
A58: 1217 | B58: 45377 | C58: David | D58: North | E58: 30387.24 | F58: 10 | G58: Furniture | H58: 2608.73 | I58: 3533.4 | J58: New | K58: 0.14 | L58: Credit Card | M58: Online | N58: =IF(ISBLANK(Table14[[#This Row],[Sales_Rep]]),"Unknown",Table14[[#This Row],[Sales_Rep]]) -> David | O58: =PROPER(Table14[[#This Row],[Region]]) -> North | P58: =IF(ISBLANK(Table14[[#This Row],[Sales_Amount]]),MEDIAN(Table14[Sales_Amount]),Table14[[#This Row],[Sales_Amount]]) -> 30387.24 | Q58: =IF(ISBLANK(Table14[[#This Row],[Quantity_Sold]]),MEDIAN(Table14[Quantity_Sold]),Table14[[#This Row],[Quantity_Sold]]) -> 10 | R58: =TRIM(Table14[[#This Row],[Product_Category]]) -> Furniture | S58: =PROPER(Table14[[#This Row],[Customer_Type]]) -> New | T58: =IF(ISBLANK(Table14[[#This Row],[Discount]]),MEDIAN(Table14[Discount]),Table14[[#This Row],[Discount]]) -> 0.14
A59: 1423 | B59: 44999 | C59: Bob | D59: West | E59: 62067.63 | F59: 19 | G59: Clothing | H59: 2479.66 | I59: 3438.65 | J59: New | K59: 0.05 | L59: Cash | M59: Retail | N59: =IF(ISBLANK(Table14[[#This Row],[Sales_Rep]]),"Unknown",Table14[[#This Row],[Sales_Rep]]) -> Bob | O59: =PROPER(Table14[[#This Row],[Region]]) -> West | P59: =IF(ISBLANK(Table14[[#This Row],[Sales_Amount]]),MEDIAN(Table14[Sales_Amount]),Table14[[#This Row],[Sales_Amount]]) -> 62067.63 | Q59: =IF(ISBLANK(Table14[[#This Row],[Quantity_Sold]]),MEDIAN(Table14[Quantity_Sold]),Table14[[#This Row],[Quantity_Sold]]) -> 19 | R59: =TRIM(Table14[[#This Row],[Product_Category]]) -> Clothing | S59: =PROPER(Table14[[#This Row],[Customer_Type]]) -> New | T59: =IF(ISBLANK(Table14[[#This Row],[Discount]]),MEDIAN(Table14[Discount]),Table14[[#This Row],[Discount]]) -> 0.05
A60: 1411 | B60: 45348 | C60: David | D60: North | E60: 108544.26 | F60: 21 | G60: Clothing | H60: 3674.06 | I60: 5384.14 | J60: Returning | K60: 0.04 | L60: Credit Card | M60: Retail | N60: =IF(ISBLANK(Table14[[#This Row],[Sales_Rep]]),"Unknown",Table14[[#This Row],[Sales_Rep]]) -> David | O60: =PROPER(Table14[[#This Row],[Region]]) -> North | P60: =IF(ISBLANK(Table14[[#This Row],[Sales_Amount]]),MEDIAN(Table14[Sales_Amount]),Table14[[#This Row],[Sales_Amount]]) -> 108544.26 | Q60: =IF(ISBLANK(Table14[[#This Row],[Quantity_Sold]]),MEDIAN(Table14[Quantity_Sold]),Table14[[#This Row],[Quantity_Sold]]) -> 21 | R60: =TRIM(Table14[[#This Row],[Product_Category]]) -> Clothing | S60: =PROPER(Table14[[#This Row],[Customer_Type]]) -> Returning | T60: =IF(ISBLANK(Table14[[#This Row],[Discount]]),MEDIAN(Table14[Discount]),Table14[[#This Row],[Discount]]) -> 0.04
A61: 1055 | B61: 45566 | C61: Bob | D61: North | E61: 61285.86 | G61: Food | H61: 3490.27 | I61: 4559.96 | J61: New | K61: 0.16 | L61: Cash | M61: Retail | N61: =IF(ISBLANK(Table14[[#This Row],[Sales_Rep]]),"Unknown",Table14[[#This Row],[Sales_Rep]]) -> Bob | O61: =PROPER(Table14[[#This Row],[Region]]) -> North | P61: =IF(ISBLANK(Table14[[#This Row],[Sales_Amount]]),MEDIAN(Table14[Sales_Amount]),Table14[[#This Row],[Sales_Amount]]) -> 61285.86 | Q61: =IF(ISBLANK(Table14[[#This Row],[Quantity_Sold]]),MEDIAN(Table14[Quantity_Sold]),Table14[[#This Row],[Quantity_Sold]]) -> 25 | R61: =TRIM(Table14[[#This Row],[Product_Category]]) -> Food | S61: =PROPER(Table14[[#This Row],[Customer_Type]]) -> New | T61: =IF(ISBLANK(Table14[[#This Row],[Discount]]),MEDIAN(Table14[Discount]),Table14[[#This Row],[Discount]]) -> 0.16
A62: 1299 | B62: 45323 | C62: Bob | D62: West | E62: 49958.77 | F62: 30 | G62: Furniture | H62: 1483.07 | I62: 2134.99 | J62: Returning | K62: 0.22 | L62: Credit Card | M62: Retail | N62: =IF(ISBLANK(Table14[[#This Row],[Sales_Rep]]),"Unknown",Table14[[#This Row],[Sales_Rep]]) -> Bob | O62: =PROPER(Table14[[#This Row],[Region]]) -> West | P62: =IF(ISBLANK(Table14[[#This Row],[Sales_Amount]]),MEDIAN(Table14[Sales_Amount]),Table14[[#This Row],[Sales_Amount]]) -> 49958.77 | Q62: =IF(ISBLANK(Table14[[#This Row],[Quantity_Sold]]),MEDIAN(Table14[Quantity_Sold]),Table14[[#This Row],[Quantity_Sold]]) -> 30 | R62: =TRIM(Table14[[#This Row],[Product_Category]]) -> Furniture | S62: =PROPER(Table14[[#This Row],[Customer_Type]]) -> Returning | T62: =IF(ISBLANK(Table14[[#This Row],[Discount]]),MEDIAN(Table14[Discount]),Table14[[#This Row],[Discount]]) -> 0.22
A63: 1015 | B63: 44945 | C63: David | D63: South | E63: 22601.17 | F63: 11 | G63: Furniture | H63: 1486.57 | I63: 2185.8 | J63: New | L63: Bank Transfer | M63: Online | N63: =IF(ISBLANK(Table14[[#This Row],[Sales_Rep]]),"Unknown",Table14[[#This Row],[Sales_Rep]]) -> David | O63: =PROPER(Table14[[#This Row],[Region]]) -> South | P63: =IF(ISBLANK(Table14[[#This Row],[Sales_Amount]]),MEDIAN(Table14[Sales_Amount]),Table14[[#This Row],[Sales_Amount]]) -> 22601.17 | Q63: =IF(ISBLANK(Table14[[#This Row],[Quantity_Sold]]),MEDIAN(Table14[Quantity_Sold]),Table14[[#This Row],[Quantity_Sold]]) -> 11 | R63: =TRIM(Table14[[#This Row],[Product_Category]]) -> Furniture | S63: =PROPER(Table14[[#This Row],[Customer_Type]]) -> New | T63: =IF(ISBLANK(Table14[[#This Row],[Discount]]),MEDIAN(Table14[Discount]),Table14[[#This Row],[Discount]]) -> 0.15
A64: 1179 | B64: 45580 | C64: Eve | D64: East | E64: 125020.4 | F64: 26 | G64: Electronics | H64: 4254.54 | I64: 5008.83 | J64: Returning | L64: Cash | M64: Retail | N64: =IF(ISBLANK(Table14[[#This Row],[Sales_Rep]]),"Unknown",Table14[[#This Row],[Sales_Rep]]) -> Eve | O64: =PROPER(Table14[[#This Row],[Region]]) -> East | P64: =IF(ISBLANK(Table14[[#This Row],[Sales_Amount]]),MEDIAN(Table14[Sales_Amount]),Table14[[#This Row],[Sales_Amount]]) -> 125020.4 | Q64: =IF(ISBLANK(Table14[[#This Row],[Quantity_Sold]]),MEDIAN(Table14[Quantity_Sold]),Table14[[#This Row],[Quantity_Sold]]) -> 26 | R64: =TRIM(Table14[[#This Row],[Product_Category]]) -> Electronics | S64: =PROPER(Table14[[#This Row],[Customer_Type]]) -> Returning | T64: =IF(ISBLANK(Table14[[#This Row],[Discount]]),MEDIAN(Table14[Discount]),Table14[[#This Row],[Discount]]) -> 0.15
A65: 1483 | B65: 45513 | C65: Bob | D65: North | E65: 56717.43 | F65: 26 | G65: Clothing | H65: 1983.32 | I65: 2371.13 | J65: Returning | K65: 0.08 | L65: Cash | M65: Online | N65: =IF(ISBLANK(Table14[[#This Row],[Sales_Rep]]),"Unknown",Table14[[#This Row],[Sales_Rep]]) -> Bob | O65: =PROPER(Table14[[#This Row],[Region]]) -> North | P65: =IF(ISBLANK(Table14[[#This Row],[Sales_Amount]]),MEDIAN(Table14[Sales_Amount]),Table14[[#This Row],[Sales_Amount]]) -> 56717.43 | Q65: =IF(ISBLANK(Table14[[#This Row],[Quantity_Sold]]),MEDIAN(Table14[Quantity_Sold]),Table14[[#This Row],[Quantity_Sold]]) -> 26 | R65: =TRIM(Table14[[#This Row],[Product_Category]]) -> Clothing | S65: =PROPER(Table14[[#This Row],[Customer_Type]]) -> Returning | T65: =IF(ISBLANK(Table14[[#This Row],[Discount]]),MEDIAN(Table14[Discount]),Table14[[#This Row],[Discount]]) -> 0.08
A66: 1358 | B66: 45149 | C66: Bob | D66: East | E66: 5824.44 | F66: 4 | G66: Clothing | H66: 1338.02 | I66: 1754.35 | J66: Returning | K66: 0.17 | L66: Bank Transfer | M66: Online | N66: =IF(ISBLANK(Table14[[#This Row],[Sales_Rep]]),"Unknown",Table14[[#This Row],[Sales_Rep]]) -> Bob | O66: =PROPER(Table14[[#This Row],[Region]]) -> East | P66: =IF(ISBLANK(Table14[[#This Row],[Sales_Amount]]),MEDIAN(Table14[Sales_Amount]),Table14[[#This Row],[Sales_Amount]]) -> 5824.44 | Q66: =IF(ISBLANK(Table14[[#This Row],[Quantity_Sold]]),MEDIAN(Table14[Quantity_Sold]),Table14[[#This Row],[Quantity_Sold]]) -> 4 | R66: =TRIM(Table14[[#This Row],[Product_Category]]) -> Clothing | S66: =PROPER(Table14[[#This Row],[Customer_Type]]) -> Returning | T66: =IF(ISBLANK(Table14[[#This Row],[Discount]]),MEDIAN(Table14[Discount]),Table14[[#This Row],[Discount]]) -> 0.17
A67: 1322 | B67: 45594 | C67: David | D67: East | E67: 92796.02 | F67: 26 | G67: Furniture | H67: 3470.09 | I67: 5026.87 | J67: New | K67: 0.29 | L67: Bank Transfer | M67: Retail | N67: =IF(ISBLANK(Table14[[#This Row],[Sales_Rep]]),"Unknown",Table14[[#This Row],[Sales_Rep]]) -> David | O67: =PROPER(Table14[[#This Row],[Region]]) -> East | P67: =IF(ISBLANK(Table14[[#This Row],[Sales_Amount]]),MEDIAN(Table14[Sales_Amount]),Table14[[#This Row],[Sales_Amount]]) -> 92796.02 | Q67: =IF(ISBLANK(Table14[[#This Row],[Quantity_Sold]]),MEDIAN(Table14[Quantity_Sold]),Table14[[#This Row],[Quantity_Sold]]) -> 26 | R67: =TRIM(Table14[[#This Row],[Product_Category]]) -> Furniture | S67: =PROPER(Table14[[#This Row],[Customer_Type]]) -> New | T67: =IF(ISBLANK(Table14[[#This Row],[Discount]]),MEDIAN(Table14[Discount]),Table14[[#This Row],[Discount]]) -> 0.29
A68: 1173 | B68: 45297 | C68: Bob | D68: North | E68: 1677.08 | F68: 2 | G68: Clothing | H68: 742.52 | I68: 873.48 | J68: Returning | K68: 0.04 | L68: Bank Transfer | M68: Retail | N68: =IF(ISBLANK(Table14[[#This Row],[Sales_Rep]]),"Unknown",Table14[[#This Row],[Sales_Rep]]) -> Bob | O68: =PROPER(Table14[[#This Row],[Region]]) -> North | P68: =IF(ISBLANK(Table14[[#This Row],[Sales_Amount]]),MEDIAN(Table14[Sales_Amount]),Table14[[#This Row],[Sales_Amount]]) -> 1677.08 | Q68: =IF(ISBLANK(Table14[[#This Row],[Quantity_Sold]]),MEDIAN(Table14[Quantity_Sold]),Table14[[#This Row],[Quantity_Sold]]) -> 2 | R68: =TRIM(Table14[[#This Row],[Product_Category]]) -> Clothing | S68: =PROPER(Table14[[#This Row],[Customer_Type]]) -> Returning | T68: =IF(ISBLANK(Table14[[#This Row],[Discount]]),MEDIAN(Table14[Discount]),Table14[[#This Row],[Discount]]) -> 0.04
A69: 1233 | B69: 45218 | C69: Bob | D69: West | E69: 1041.78 | F69: 1 | G69: Electronics | H69: 865.93 | I69: 1144.81 | J69: New | K69: 0.09 | L69: Credit Card | M69: Online | N69: =IF(ISBLANK(Table14[[#This Row],[Sales_Rep]]),"Unknown",Table14[[#This Row],[Sales_Rep]]) -> Bob | O69: =PROPER(Table14[[#This Row],[Region]]) -> West | P69: =IF(ISBLANK(Table14[[#This Row],[Sales_Amount]]),MEDIAN(Table14[Sales_Amount]),Table14[[#This Row],[Sales_Amount]]) -> 1041.78 | Q69: =IF(ISBLANK(Table14[[#This Row],[Quantity_Sold]]),MEDIAN(Table14[Quantity_Sold]),Table14[[#This Row],[Quantity_Sold]]) -> 1 | R69: =TRIM(Table14[[#This Row],[Product_Category]]) -> Electronics | S69: =PROPER(Table14[[#This Row],[Customer_Type]]) -> New | T69: =IF(ISBLANK(Table14[[#This Row],[Discount]]),MEDIAN(Table14[Discount]),Table14[[#This Row],[Discount]]) -> 0.09
A70: 1452 | B70: 45060 | C70: David | D70: East | F70: 29 | G70: Furniture | H70: 4954.07 | I70: 7017.06 | J70: New | K70: 0.3 | L70: Cash | M70: Online | N70: =IF(ISBLANK(Table14[[#This Row],[Sales_Rep]]),"Unknown",Table14[[#This Row],[Sales_Rep]]) -> David | O70: =PROPER(Table14[[#This Row],[Region]]) -> East | P70: =IF(ISBLANK(Table14[[#This Row],[Sales_Amount]]),MEDIAN(Table14[Sales_Amount]),Table14[[#This Row],[Sales_Amount]]) -> 50770.89 | Q70: =IF(ISBLANK(Table14[[#This Row],[Quantity_Sold]]),MEDIAN(Table14[Quantity_Sold]),Table14[[#This Row],[Quantity_Sold]]) -> 29 | R70: =TRIM(Table14[[#This Row],[Product_Category]]) -> Furniture | S70: =PROPER(Table14[[#This Row],[Customer_Type]]) -> New | T70: =IF(ISBLANK(Table14[[#This Row],[Discount]]),MEDIAN(Table14[Discount]),Table14[[#This Row],[Discount]]) -> 0.3
A71: 1361 | B71: 45588 | C71: David | D71: North | F71: 8 | G71: Food | H71: 1363.39 | I71: 1981.6 | J71: Returning | K71: 0.17 | L71: Credit Card | M71: Online | N71: =IF(ISBLANK(Table14[[#This Row],[Sales_Rep]]),"Unknown",Table14[[#This Row],[Sales_Rep]]) -> David | O71: =PROPER(Table14[[#This Row],[Region]]) -> North | P71: =IF(ISBLANK(Table14[[#This Row],[Sales_Amount]]),MEDIAN(Table14[Sales_Amount]),Table14[[#This Row],[Sales_Amount]]) -> 50770.89 | Q71: =IF(ISBLANK(Table14[[#This Row],[Quantity_Sold]]),MEDIAN(Table14[Quantity_Sold]),Table14[[#This Row],[Quantity_Sold]]) -> 8 | R71: =TRIM(Table14[[#This Row],[Product_Category]]) -> Food | S71: =PROPER(Table14[[#This Row],[Customer_Type]]) -> Returning | T71: =IF(ISBLANK(Table14[[#This Row],[Discount]]),MEDIAN(Table14[Discount]),Table14[[#This Row],[Discount]]) -> 0.17
A72: 1402 | B72: 45183 | C72: Alice | D72: West | E72: 119838.05 | F72: 29 | G72: Clothing | H72: 3728.06 | I72: 4919.46 | J72: Returning | K72: 0.16 | L72: Credit Card | M72: Retail | N72: =IF(ISBLANK(Table14[[#This Row],[Sales_Rep]]),"Unknown",Table14[[#This Row],[Sales_Rep]]) -> Alice | O72: =PROPER(Table14[[#This Row],[Region]]) -> West | P72: =IF(ISBLANK(Table14[[#This Row],[Sales_Amount]]),MEDIAN(Table14[Sales_Amount]),Table14[[#This Row],[Sales_Amount]]) -> 119838.05 | Q72: =IF(ISBLANK(Table14[[#This Row],[Quantity_Sold]]),MEDIAN(Table14[Quantity_Sold]),Table14[[#This Row],[Quantity_Sold]]) -> 29 | R72: =TRIM(Table14[[#This Row],[Product_Category]]) -> Clothing | S72: =PROPER(Table14[[#This Row],[Customer_Type]]) -> Returning | T72: =IF(ISBLANK(Table14[[#This Row],[Discount]]),MEDIAN(Table14[Discount]),Table14[[#This Row],[Discount]]) -> 0.16
A73: 1254 | B73: 45036 | C73: Eve | D73: South | E73: 165705.75 | F73: 50 | G73: Clothing | H73: 3686.78 | I73: 4091.5 | J73: Returning | K73: 0.19 | L73: Cash | M73: Online | N73: =IF(ISBLANK(Table14[[#This Row],[Sales_Rep]]),"Unknown",Table14[[#This Row],[Sales_Rep]]) -> Eve | O73: =PROPER(Table14[[#This Row],[Region]]) -> South | P73: =IF(ISBLANK(Table14[[#This Row],[Sales_Amount]]),MEDIAN(Table14[Sales_Amount]),Table14[[#This Row],[Sales_Amount]]) -> 165705.75 | Q73: =IF(ISBLANK(Table14[[#This Row],[Quantity_Sold]]),MEDIAN(Table14[Quantity_Sold]),Table14[[#This Row],[Quantity_Sold]]) -> 50 | R73: =TRIM(Table14[[#This Row],[Product_Category]]) -> Clothing | S73: =PROPER(Table14[[#This Row],[Customer_Type]]) -> Returning | T73: =IF(ISBLANK(Table14[[#This Row],[Discount]]),MEDIAN(Table14[Discount]),Table14[[#This Row],[Discount]]) -> 0.19
A74: 1224 | B74: 45174 | C74: Eve | D74: East | E74: 240585.97 | F74: 44 | G74: Food | H74: 4497.34 | I74: 6284.9 | J74: New | K74: 0.13 | L74: Credit Card | M74: Retail | N74: =IF(ISBLANK(Table14[[#This Row],[Sales_Rep]]),"Unknown",Table14[[#This Row],[Sales_Rep]]) -> Eve | O74: =PROPER(Table14[[#This Row],[Region]]) -> East | P74: =IF(ISBLANK(Table14[[#This Row],[Sales_Amount]]),MEDIAN(Table14[Sales_Amount]),Table14[[#This Row],[Sales_Amount]]) -> 240585.97 | Q74: =IF(ISBLANK(Table14[[#This Row],[Quantity_Sold]]),MEDIAN(Table14[Quantity_Sold]),Table14[[#This Row],[Quantity_Sold]]) -> 44 | R74: =TRIM(Table14[[#This Row],[Product_Category]]) -> Food | S74: =PROPER(Table14[[#This Row],[Customer_Type]]) -> New | T74: =IF(ISBLANK(Table14[[#This Row],[Discount]]),MEDIAN(Table14[Discount]),Table14[[#This Row],[Discount]]) -> 0.13
A75: 1303 | B75: 45054 | C75: Bob | D75: North | E75: 54405.76 | F75: 40 | G75: Electronics | H75: 1151.16 | I75: 1679.19 | J75: Returning | K75: 0.19 | L75: Bank Transfer | M75: Online | N75: =IF(ISBLANK(Table14[[#This Row],[Sales_Rep]]),"Unknown",Table14[[#This Row],[Sales_Rep]]) -> Bob | O75: =PROPER(Table14[[#This Row],[Region]]) -> North | P75: =IF(ISBLANK(Table14[[#This Row],[Sales_Amount]]),MEDIAN(Table14[Sales_Amount]),Table14[[#This Row],[Sales_Amount]]) -> 54405.76 | Q75: =IF(ISBLANK(Table14[[#This Row],[Quantity_Sold]]),MEDIAN(Table14[Quantity_Sold]),Table14[[#This Row],[Quantity_Sold]]) -> 40 | R75: =TRIM(Table14[[#This Row],[Product_Category]]) -> Electronics | S75: =PROPER(Table14[[#This Row],[Customer_Type]]) -> Returning | T75: =IF(ISBLANK(Table14[[#This Row],[Discount]]),MEDIAN(Table14[Discount]),Table14[[#This Row],[Discount]]) -> 0.19
A76: 1219 | B76: 45039 | C76: Eve | D76: West | E76: 184386.15 | F76: 50 | G76: Clothing | H76: 3267.79 | I76: 4288.05 | J76: New | K76: 0.14 | L76: Bank Transfer | M76: Online | N76: =IF(ISBLANK(Table14[[#This Row],[Sales_Rep]]),"Unknown",Table14[[#This Row],[Sales_Rep]]) -> Eve | O76: =PROPER(Table14[[#This Row],[Region]]) -> West | P76: =IF(ISBLANK(Table14[[#This Row],[Sales_Amount]]),MEDIAN(Table14[Sales_Amount]),Table14[[#This Row],[Sales_Amount]]) -> 184386.15 | Q76: =IF(ISBLANK(Table14[[#This Row],[Quantity_Sold]]),MEDIAN(Table14[Quantity_Sold]),Table14[[#This Row],[Quantity_Sold]]) -> 50 | R76: =TRIM(Table14[[#This Row],[Product_Category]]) -> Clothing | S76: =PROPER(Table14[[#This Row],[Customer_Type]]) -> New | T76: =IF(ISBLANK(Table14[[#This Row],[Discount]]),MEDIAN(Table14[Discount]),Table14[[#This Row],[Discount]]) -> 0.14
A77: 1080 | B77: 45090 | C77: Bob | D77: North | E77: 170038.41 | F77: 31 | G77: Clothing | H77: 3873.58 | I77: 5773.8 | J77: New | K77: 0.05 | L77: Cash | M77: Online | N77: =IF(ISBLANK(Table14[[#This Row],[Sales_Rep]]),"Unknown",Table14[[#This Row],[Sales_Rep]]) -> Bob | O77: =PROPER(Table14[[#This Row],[Region]]) -> North | P77: =IF(ISBLANK(Table14[[#This Row],[Sales_Amount]]),MEDIAN(Table14[Sales_Amount]),Table14[[#This Row],[Sales_Amount]]) -> 170038.41 | Q77: =IF(ISBLANK(Table14[[#This Row],[Quantity_Sold]]),MEDIAN(Table14[Quantity_Sold]),Table14[[#This Row],[Quantity_Sold]]) -> 31 | R77: =TRIM(Table14[[#This Row],[Product_Category]]) -> Clothing | S77: =PROPER(Table14[[#This Row],[Customer_Type]]) -> New | T77: =IF(ISBLANK(Table14[[#This Row],[Discount]]),MEDIAN(Table14[Discount]),Table14[[#This Row],[Discount]]) -> 0.05
A78: 1159 | B78: 45516 | C78: Alice | D78: North | E78: 63436.59 | F78: 28 | G78: Clothing | H78: 1758.65 | I78: 2634.41 | J78: New | K78: 0.14 | L78: Bank Transfer | M78: Online | N78: =IF(ISBLANK(Table14[[#This Row],[Sales_Rep]]),"Unknown",Table14[[#This Row],[Sales_Rep]]) -> Alice | O78: =PROPER(Table14[[#This Row],[Region]]) -> North | P78: =IF(ISBLANK(Table14[[#This Row],[Sales_Amount]]),MEDIAN(Table14[Sales_Amount]),Table14[[#This Row],[Sales_Amount]]) -> 63436.59 | Q78: =IF(ISBLANK(Table14[[#This Row],[Quantity_Sold]]),MEDIAN(Table14[Quantity_Sold]),Table14[[#This Row],[Quantity_Sold]]) -> 28 | R78: =TRIM(Table14[[#This Row],[Product_Category]]) -> Clothing | S78: =PROPER(Table14[[#This Row],[Customer_Type]]) -> New | T78: =IF(ISBLANK(Table14[[#This Row],[Discount]]),MEDIAN(Table14[Discount]),Table14[[#This Row],[Discount]]) -> 0.14
A79: 1066 | B79: 45141 | C79: David | D79: North | E79: 19792.09 | F79: 28 | G79: Clothing | H79: 754.24 | I79: 894.76 | J79: New | K79: 0.21 | L79: Credit Card | M79: Online | N79: =IF(ISBLANK(Table14[[#This Row],[Sales_Rep]]),"Unknown",Table14[[#This Row],[Sales_Rep]]) -> David | O79: =PROPER(Table14[[#This Row],[Region]]) -> North | P79: =IF(ISBLANK(Table14[[#This Row],[Sales_Amount]]),MEDIAN(Table14[Sales_Amount]),Table14[[#This Row],[Sales_Amount]]) -> 19792.09 | Q79: =IF(ISBLANK(Table14[[#This Row],[Quantity_Sold]]),MEDIAN(Table14[Quantity_Sold]),Table14[[#This Row],[Quantity_Sold]]) -> 28 | R79: =TRIM(Table14[[#This Row],[Product_Category]]) -> Clothing | S79: =PROPER(Table14[[#This Row],[Customer_Type]]) -> New | T79: =IF(ISBLANK(Table14[[#This Row],[Discount]]),MEDIAN(Table14[Discount]),Table14[[#This Row],[Discount]]) -> 0.21
A80: 1302 | B80: 45315 | C80: David | D80: West | E80: 102265.87 | F80: 33 | G80: Furniture | H80: 2323.16 | I80: 3162.21 | J80: New | K80: 0.02 | L80: Cash | M80: Retail | N80: =IF(ISBLANK(Table14[[#This Row],[Sales_Rep]]),"Unknown",Table14[[#This Row],[Sales_Rep]]) -> David | O80: =PROPER(Table14[[#This Row],[Region]]) -> West | P80: =IF(ISBLANK(Table14[[#This Row],[Sales_Amount]]),MEDIAN(Table14[Sales_Amount]),Table14[[#This Row],[Sales_Amount]]) -> 102265.87 | Q80: =IF(ISBLANK(Table14[[#This Row],[Quantity_Sold]]),MEDIAN(Table14[Quantity_Sold]),Table14[[#This Row],[Quantity_Sold]]) -> 33 | R80: =TRIM(Table14[[#This Row],[Product_Category]]) -> Furniture | S80: =PROPER(Table14[[#This Row],[Customer_Type]]) -> New | T80: =IF(ISBLANK(Table14[[#This Row],[Discount]]),MEDIAN(Table14[Discount]),Table14[[#This Row],[Discount]]) -> 0.02
A81: 1148 | B81: 45217 | D81: North | E81: 121832.4 | F81: 50 | G81: Clothing | H81: 2346.51 | I81: 3045.81 | J81: New | K81: 0.2 | L81: Credit Card | M81: Retail | N81: =IF(ISBLANK(Table14[[#This Row],[Sales_Rep]]),"Unknown",Table14[[#This Row],[Sales_Rep]]) -> Unknown | O81: =PROPER(Table14[[#This Row],[Region]]) -> North | P81: =IF(ISBLANK(Table14[[#This Row],[Sales_Amount]]),MEDIAN(Table14[Sales_Amount]),Table14[[#This Row],[Sales_Amount]]) -> 121832.4 | Q81: =IF(ISBLANK(Table14[[#This Row],[Quantity_Sold]]),MEDIAN(Table14[Quantity_Sold]),Table14[[#This Row],[Quantity_Sold]]) -> 50 | R81: =TRIM(Table14[[#This Row],[Product_Category]]) -> Clothing | S81: =PROPER(Table14[[#This Row],[Customer_Type]]) -> New | T81: =IF(ISBLANK(Table14[[#This Row],[Discount]]),MEDIAN(Table14[Discount]),Table14[[#This Row],[Discount]]) -> 0.2
A82: 1197 | B82: 45037 | C82: Eve | D82: North | E82: 64521.8 | F82: 38 | G82: Furniture | H82: 1623.03 | I82: 1907.8 | J82: Returning | K82: 0.11 | L82: Cash | M82: Retail | N82: =IF(ISBLANK(Table14[[#This Row],[Sales_Rep]]),"Unknown",Table14[[#This Row],[Sales_Rep]]) -> Eve | O82: =PROPER(Table14[[#This Row],[Region]]) -> North | P82: =IF(ISBLANK(Table14[[#This Row],[Sales_Amount]]),MEDIAN(Table14[Sales_Amount]),Table14[[#This Row],[Sales_Amount]]) -> 64521.8 | Q82: =IF(ISBLANK(Table14[[#This Row],[Quantity_Sold]]),MEDIAN(Table14[Quantity_Sold]),Table14[[#This Row],[Quantity_Sold]]) -> 38 | R82: =TRIM(Table14[[#This Row],[Product_Category]]) -> Furniture | S82: =PROPER(Table14[[#This Row],[Customer_Type]]) -> Returning | T82: =IF(ISBLANK(Table14[[#This Row],[Discount]]),MEDIAN(Table14[Discount]),Table14[[#This Row],[Discount]]) -> 0.11
A83: 1159 | B83: 45130 | C83: Alice | D83: South | E83: 19436.73 | F83: 48 | G83: Food | H83: 305.69 | I83: 444.98 | J83: Returning | K83: 0.09 | L83: Credit Card | M83: Retail | N83: =IF(ISBLANK(Table14[[#This Row],[Sales_Rep]]),"Unknown",Table14[[#This Row],[Sales_Rep]]) -> Alice | O83: =PROPER(Table14[[#This Row],[Region]]) -> South | P83: =IF(ISBLANK(Table14[[#This Row],[Sales_Amount]]),MEDIAN(Table14[Sales_Amount]),Table14[[#This Row],[Sales_Amount]]) -> 19436.73 | Q83: =IF(ISBLANK(Table14[[#This Row],[Quantity_Sold]]),MEDIAN(Table14[Quantity_Sold]),Table14[[#This Row],[Quantity_Sold]]) -> 48 | R83: =TRIM(Table14[[#This Row],[Product_Category]]) -> Food | S83: =PROPER(Table14[[#This Row],[Customer_Type]]) -> Returning | T83: =IF(ISBLANK(Table14[[#This Row],[Discount]]),MEDIAN(Table14[Discount]),Table14[[#This Row],[Discount]]) -> 0.09
A84: 1110 | B84: 45507 | C84: Eve | D84: North | E84: 20761.68 | F84: 7 | G84: Food | H84: 2437.05 | I84: 3155.27 | J84: Returning | K84: 0.06 | L84: Bank Transfer | M84: Online | N84: =IF(ISBLANK(Table14[[#This Row],[Sales_Rep]]),"Unknown",Table14[[#This Row],[Sales_Rep]]) -> Eve | O84: =PROPER(Table14[[#This Row],[Region]]) -> North | P84: =IF(ISBLANK(Table14[[#This Row],[Sales_Amount]]),MEDIAN(Table14[Sales_Amount]),Table14[[#This Row],[Sales_Amount]]) -> 20761.68 | Q84: =IF(ISBLANK(Table14[[#This Row],[Quantity_Sold]]),MEDIAN(Table14[Quantity_Sold]),Table14[[#This Row],[Quantity_Sold]]) -> 7 | R84: =TRIM(Table14[[#This Row],[Product_Category]]) -> Food | S84: =PROPER(Table14[[#This Row],[Customer_Type]]) -> Returning | T84: =IF(ISBLANK(Table14[[#This Row],[Discount]]),MEDIAN(Table14[Discount]),Table14[[#This Row],[Discount]]) -> 0.06
A85: 1154 | B85: 45274 | C85: Eve | D85: North | E85: 203247.37 | F85: 49 | G85: Clothing | H85: 4172.68 | I85: 5760.98 | J85: Returning | K85: 0.28 | L85: Bank Transfer | M85: Retail | N85: =IF(ISBLANK(Table14[[#This Row],[Sales_Rep]]),"Unknown",Table14[[#This Row],[Sales_Rep]]) -> Eve | O85: =PROPER(Table14[[#This Row],[Region]]) -> North | P85: =IF(ISBLANK(Table14[[#This Row],[Sales_Amount]]),MEDIAN(Table14[Sales_Amount]),Table14[[#This Row],[Sales_Amount]]) -> 203247.37 | Q85: =IF(ISBLANK(Table14[[#This Row],[Quantity_Sold]]),MEDIAN(Table14[Quantity_Sold]),Table14[[#This Row],[Quantity_Sold]]) -> 49 | R85: =TRIM(Table14[[#This Row],[Product_Category]]) -> Clothing | S85: =PROPER(Table14[[#This Row],[Customer_Type]]) -> Returning | T85: =IF(ISBLANK(Table14[[#This Row],[Discount]]),MEDIAN(Table14[Discount]),Table14[[#This Row],[Discount]]) -> 0.28
A86: 1490 | B86: 45321 | C86: Alice | D86: West | F86: 27 | G86: Food | H86: 4796.56 | I86: 6882.36 | J86: Returning | K86: 0.3 | L86: Bank Transfer | M86: Online | N86: =IF(ISBLANK(Table14[[#This Row],[Sales_Rep]]),"Unknown",Table14[[#This Row],[Sales_Rep]]) -> Alice | O86: =PROPER(Table14[[#This Row],[Region]]) -> West | P86: =IF(ISBLANK(Table14[[#This Row],[Sales_Amount]]),MEDIAN(Table14[Sales_Amount]),Table14[[#This Row],[Sales_Amount]]) -> 50770.89 | Q86: =IF(ISBLANK(Table14[[#This Row],[Quantity_Sold]]),MEDIAN(Table14[Quantity_Sold]),Table14[[#This Row],[Quantity_Sold]]) -> 27 | R86: =TRIM(Table14[[#This Row],[Product_Category]]) -> Food | S86: =PROPER(Table14[[#This Row],[Customer_Type]]) -> Returning | T86: =IF(ISBLANK(Table14[[#This Row],[Discount]]),MEDIAN(Table14[Discount]),Table14[[#This Row],[Discount]]) -> 0.3
A87: 1224 | B87: 44985 | C87: Alice | D87: East | F87: 46 | G87: Clothing | H87: 830 | I87: 1026.55 | J87: Returning | L87: Cash | M87: Retail | N87: =IF(ISBLANK(Table14[[#This Row],[Sales_Rep]]),"Unknown",Table14[[#This Row],[Sales_Rep]]) -> Alice | O87: =PROPER(Table14[[#This Row],[Region]]) -> East | P87: =IF(ISBLANK(Table14[[#This Row],[Sales_Amount]]),MEDIAN(Table14[Sales_Amount]),Table14[[#This Row],[Sales_Amount]]) -> 50770.89 | Q87: =IF(ISBLANK(Table14[[#This Row],[Quantity_Sold]]),MEDIAN(Table14[Quantity_Sold]),Table14[[#This Row],[Quantity_Sold]]) -> 46 | R87: =TRIM(Table14[[#This Row],[Product_Category]]) -> Clothing | S87: =PROPER(Table14[[#This Row],[Customer_Type]]) -> Returning | T87: =IF(ISBLANK(Table14[[#This Row],[Discount]]),MEDIAN(Table14[Discount]),Table14[[#This Row],[Discount]]) -> 0.15
A88: 1143 | B88: 45291 | C88: Alice | D88: West | E88: 131360.78 | F88: 50 | G88: Furniture | H88: 2365.38 | I88: 3165.32 | J88: Returning | L88: Bank Transfer | M88: Retail | N88: =IF(ISBLANK(Table14[[#This Row],[Sales_Rep]]),"Unknown",Table14[[#This Row],[Sales_Rep]]) -> Alice | O88: =PROPER(Table14[[#This Row],[Region]]) -> West | P88: =IF(ISBLANK(Table14[[#This Row],[Sales_Amount]]),MEDIAN(Table14[Sales_Amount]),Table14[[#This Row],[Sales_Amount]]) -> 131360.78 | Q88: =IF(ISBLANK(Table14[[#This Row],[Quantity_Sold]]),MEDIAN(Table14[Quantity_Sold]),Table14[[#This Row],[Quantity_Sold]]) -> 50 | R88: =TRIM(Table14[[#This Row],[Product_Category]]) -> Furniture | S88: =PROPER(Table14[[#This Row],[Customer_Type]]) -> Returning | T88: =IF(ISBLANK(Table14[[#This Row],[Discount]]),MEDIAN(Table14[Discount]),Table14[[#This Row],[Discount]]) -> 0.15
A89: 1431 | B89: 45377 | C89: Alice | D89: North | E89: 84527.35 | F89: 21 | G89: Food | H89: 3763.71 | I89: 4236.96 | J89: Returning | K89: 0.05 | L89: Bank Transfer | M89: Retail | N89: =IF(ISBLANK(Table14[[#This Row],[Sales_Rep]]),"Unknown",Table14[[#This Row],[Sales_Rep]]) -> Alice | O89: =PROPER(Table14[[#This Row],[Region]]) -> North | P89: =IF(ISBLANK(Table14[[#This Row],[Sales_Amount]]),MEDIAN(Table14[Sales_Amount]),Table14[[#This Row],[Sales_Amount]]) -> 84527.35 | Q89: =IF(ISBLANK(Table14[[#This Row],[Quantity_Sold]]),MEDIAN(Table14[Quantity_Sold]),Table14[[#This Row],[Quantity_Sold]]) -> 21 | R89: =TRIM(Table14[[#This Row],[Product_Category]]) -> Food | S89: =PROPER(Table14[[#This Row],[Customer_Type]]) -> Returning | T89: =IF(ISBLANK(Table14[[#This Row],[Discount]]),MEDIAN(Table14[Discount]),Table14[[#This Row],[Discount]]) -> 0.05
A90: 1071 | B90: 45272 | C90: David | D90: West | E90: 9866.88 | F90: 12 | G90: Food | H90: 591.86 | I90: 839.02 | J90: New | K90: 0.02 | L90: Credit Card | M90: Online | N90: =IF(ISBLANK(Table14[[#This Row],[Sales_Rep]]),"Unknown",Table14[[#This Row],[Sales_Rep]]) -> David | O90: =PROPER(Table14[[#This Row],[Region]]) -> West | P90: =IF(ISBLANK(Table14[[#This Row],[Sales_Amount]]),MEDIAN(Table14[Sales_Amount]),Table14[[#This Row],[Sales_Amount]]) -> 9866.88 | Q90: =IF(ISBLANK(Table14[[#This Row],[Quantity_Sold]]),MEDIAN(Table14[Quantity_Sold]),Table14[[#This Row],[Quantity_Sold]]) -> 12 | R90: =TRIM(Table14[[#This Row],[Product_Category]]) -> Food | S90: =PROPER(Table14[[#This Row],[Customer_Type]]) -> New | T90: =IF(ISBLANK(Table14[[#This Row],[Discount]]),MEDIAN(Table14[Discount]),Table14[[#This Row],[Discount]]) -> 0.02
A91: 1125 | B91: 45418 | C91: Charlie | D91: East | E91: 72239.76 | F91: 15 | G91: Clothing | H91: 4919.18 | I91: 5802.39 | J91: Returning | K91: 0.17 | L91: Credit Card | M91: Retail | N91: =IF(ISBLANK(Table14[[#This Row],[Sales_Rep]]),"Unknown",Table14[[#This Row],[Sales_Rep]]) -> Charlie | O91: =PROPER(Table14[[#This Row],[Region]]) -> East | P91: =IF(ISBLANK(Table14[[#This Row],[Sales_Amount]]),MEDIAN(Table14[Sales_Amount]),Table14[[#This Row],[Sales_Amount]]) -> 72239.76 | Q91: =IF(ISBLANK(Table14[[#This Row],[Quantity_Sold]]),MEDIAN(Table14[Quantity_Sold]),Table14[[#This Row],[Quantity_Sold]]) -> 15 | R91: =TRIM(Table14[[#This Row],[Product_Category]]) -> Clothing | S91: =PROPER(Table14[[#This Row],[Customer_Type]]) -> Returning | T91: =IF(ISBLANK(Table14[[#This Row],[Discount]]),MEDIAN(Table14[Discount]),Table14[[#This Row],[Discount]]) -> 0.17
A92: 1335 | B92: 45032 | C92: Charlie | D92: North | E92: 147801.78 | F92: 36 | G92: Clothing | H92: 3898.11 | I92: 5474.14 | J92: New | K92: 0.25 | L92: Bank Transfer | M92: Retail | N92: =IF(ISBLANK(Table14[[#This Row],[Sales_Rep]]),"Unknown",Table14[[#This Row],[Sales_Rep]]) -> Charlie | O92: =PROPER(Table14[[#This Row],[Region]]) -> North | P92: =IF(ISBLANK(Table14[[#This Row],[Sales_Amount]]),MEDIAN(Table14[Sales_Amount]),Table14[[#This Row],[Sales_Amount]]) -> 147801.78 | Q92: =IF(ISBLANK(Table14[[#This Row],[Quantity_Sold]]),MEDIAN(Table14[Quantity_Sold]),Table14[[#This Row],[Quantity_Sold]]) -> 36 | R92: =TRIM(Table14[[#This Row],[Product_Category]]) -> Clothing | S92: =PROPER(Table14[[#This Row],[Customer_Type]]) -> New | T92: =IF(ISBLANK(Table14[[#This Row],[Discount]]),MEDIAN(Table14[Discount]),Table14[[#This Row],[Discount]]) -> 0.25
A93: 1258 | B93: 45526 | C93: Alice | D93: West | E93: 148353.75 | F93: 48 | G93: Electronics | H93: 2408.92 | I93: 3359.46 | J93: Returning | K93: 0.08 | L93: Cash | M93: Retail | N93: =IF(ISBLANK(Table14[[#This Row],[Sales_Rep]]),"Unknown",Table14[[#This Row],[Sales_Rep]]) -> Alice | O93: =PROPER(Table14[[#This Row],[Region]]) -> West | P93: =IF(ISBLANK(Table14[[#This Row],[Sales_Amount]]),MEDIAN(Table14[Sales_Amount]),Table14[[#This Row],[Sales_Amount]]) -> 148353.75 | Q93: =IF(ISBLANK(Table14[[#This Row],[Quantity_Sold]]),MEDIAN(Table14[Quantity_Sold]),Table14[[#This Row],[Quantity_Sold]]) -> 48 | R93: =TRIM(Table14[[#This Row],[Product_Category]]) -> Electronics | S93: =PROPER(Table14[[#This Row],[Customer_Type]]) -> Returning | T93: =IF(ISBLANK(Table14[[#This Row],[Discount]]),MEDIAN(Table14[Discount]),Table14[[#This Row],[Discount]]) -> 0.08
A94: 1062 | B94: 45234 | C94: Charlie | D94: South | E94: 64148.57 | F94: 17 | G94: Food | H94: 3323.14 | I94: 3890.15 | J94: New | K94: 0.03 | L94: Bank Transfer | M94: Retail | N94: =IF(ISBLANK(Table14[[#This Row],[Sales_Rep]]),"Unknown",Table14[[#This Row],[Sales_Rep]]) -> Charlie | O94: =PROPER(Table14[[#This Row],[Region]]) -> South | P94: =IF(ISBLANK(Table14[[#This Row],[Sales_Amount]]),MEDIAN(Table14[Sales_Amount]),Table14[[#This Row],[Sales_Amount]]) -> 64148.57 | Q94: =IF(ISBLANK(Table14[[#This Row],[Quantity_Sold]]),MEDIAN(Table14[Quantity_Sold]),Table14[[#This Row],[Quantity_Sold]]) -> 17 | R94: =TRIM(Table14[[#This Row],[Product_Category]]) -> Food | S94: =PROPER(Table14[[#This Row],[Customer_Type]]) -> New | T94: =IF(ISBLANK(Table14[[#This Row],[Discount]]),MEDIAN(Table14[Discount]),Table14[[#This Row],[Discount]]) -> 0.03
A95: 1477 | B95: 44997 | C95: Charlie | D95: East | E95: 62587.92 | F95: 14 | G95: Electronics | H95: 4274.77 | I95: 4807.06 | J95: Returning | K95: 0.07 | L95: Cash | M95: Online | N95: =IF(ISBLANK(Table14[[#This Row],[Sales_Rep]]),"Unknown",Table14[[#This Row],[Sales_Rep]]) -> Charlie | O95: =PROPER(Table14[[#This Row],[Region]]) -> East | P95: =IF(ISBLANK(Table14[[#This Row],[Sales_Amount]]),MEDIAN(Table14[Sales_Amount]),Table14[[#This Row],[Sales_Amount]]) -> 62587.92 | Q95: =IF(ISBLANK(Table14[[#This Row],[Quantity_Sold]]),MEDIAN(Table14[Quantity_Sold]),Table14[[#This Row],[Quantity_Sold]]) -> 14 | R95: =TRIM(Table14[[#This Row],[Product_Category]]) -> Electronics | S95: =PROPER(Table14[[#This Row],[Customer_Type]]) -> Returning | T95: =IF(ISBLANK(Table14[[#This Row],[Discount]]),MEDIAN(Table14[Discount]),Table14[[#This Row],[Discount]]) -> 0.07
A96: 1395 | B96: 44981 | C96: Alice | D96: South | F96: 13 | G96: Food | H96: 3800.09 | I96: 4369.48 | J96: New | K96: 0.21 | L96: Cash | M96: Retail | N96: =IF(ISBLANK(Table14[[#This Row],[Sales_Rep]]),"Unknown",Table14[[#This Row],[Sales_Rep]]) -> Alice | O96: =PROPER(Table14[[#This Row],[Region]]) -> South | P96: =IF(ISBLANK(Table14[[#This Row],[Sales_Amount]]),MEDIAN(Table14[Sales_Amount]),Table14[[#This Row],[Sales_Amount]]) -> 50770.89 | Q96: =IF(ISBLANK(Table14[[#This Row],[Quantity_Sold]]),MEDIAN(Table14[Quantity_Sold]),Table14[[#This Row],[Quantity_Sold]]) -> 13 | R96: =TRIM(Table14[[#This Row],[Product_Category]]) -> Food | S96: =PROPER(Table14[[#This Row],[Customer_Type]]) -> New | T96: =IF(ISBLANK(Table14[[#This Row],[Discount]]),MEDIAN(Table14[Discount]),Table14[[#This Row],[Discount]]) -> 0.21
A97: 1084 | B97: 45138 | C97: Charlie | D97: East | F97: 7 | G97: Food | H97: 90.87 | I97: 132.25 | J97: Returning | K97: 0.05 | L97: Cash | M97: Retail | N97: =IF(ISBLANK(Table14[[#This Row],[Sales_Rep]]),"Unknown",Table14[[#This Row],[Sales_Rep]]) -> Charlie | O97: =PROPER(Table14[[#This Row],[Region]]) -> East | P97: =IF(ISBLANK(Table14[[#This Row],[Sales_Amount]]),MEDIAN(Table14[Sales_Amount]),Table14[[#This Row],[Sales_Amount]]) -> 50770.89 | Q97: =IF(ISBLANK(Table14[[#This Row],[Quantity_Sold]]),MEDIAN(Table14[Quantity_Sold]),Table14[[#This Row],[Quantity_Sold]]) -> 7 | R97: =TRIM(Table14[[#This Row],[Product_Category]]) -> Food | S97: =PROPER(Table14[[#This Row],[Customer_Type]]) -> Returning | T97: =IF(ISBLANK(Table14[[#This Row],[Discount]]),MEDIAN(Table14[Discount]),Table14[[#This Row],[Discount]]) -> 0.05
A98: 1017 | B98: 44987 | C98: Eve | D98: West | E98: 116881.32 | F98: 34 | G98: Furniture | H98: 4168.23 | I98: 4910.98 | J98: Returning | K98: 0.3 | L98: Cash | M98: Retail | N98: =IF(ISBLANK(Table14[[#This Row],[Sales_Rep]]),"Unknown",Table14[[#This Row],[Sales_Rep]]) -> Eve | O98: =PROPER(Table14[[#This Row],[Region]]) -> West | P98: =IF(ISBLANK(Table14[[#This Row],[Sales_Amount]]),MEDIAN(Table14[Sales_Amount]),Table14[[#This Row],[Sales_Amount]]) -> 116881.32 | Q98: =IF(ISBLANK(Table14[[#This Row],[Quantity_Sold]]),MEDIAN(Table14[Quantity_Sold]),Table14[[#This Row],[Quantity_Sold]]) -> 34 | R98: =TRIM(Table14[[#This Row],[Product_Category]]) -> Furniture | S98: =PROPER(Table14[[#This Row],[Customer_Type]]) -> Returning | T98: =IF(ISBLANK(Table14[[#This Row],[Discount]]),MEDIAN(Table14[Discount]),Table14[[#This Row],[Discount]]) -> 0.3
A99: 1033 | B99: 45393 | C99: Bob | D99: West | E99: 170058.7 | F99: 37 | G99: Electronics | H99: 3929.13 | I99: 5892.54 | J99: New | K99: 0.22 | L99: Credit Card | M99: Online | N99: =IF(ISBLANK(Table14[[#This Row],[Sales_Rep]]),"Unknown",Table14[[#This Row],[Sales_Rep]]) -> Bob | O99: =PROPER(Table14[[#This Row],[Region]]) -> West | P99: =IF(ISBLANK(Table14[[#This Row],[Sales_Amount]]),MEDIAN(Table14[Sales_Amount]),Table14[[#This Row],[Sales_Amount]]) -> 170058.7 | Q99: =IF(ISBLANK(Table14[[#This Row],[Quantity_Sold]]),MEDIAN(Table14[Quantity_Sold]),Table14[[#This Row],[Quantity_Sold]]) -> 37 | R99: =TRIM(Table14[[#This Row],[Product_Category]]) -> Electronics | S99: =PROPER(Table14[[#This Row],[Customer_Type]]) -> New | T99: =IF(ISBLANK(Table14[[#This Row],[Discount]]),MEDIAN(Table14[Discount]),Table14[[#This Row],[Discount]]) -> 0.22
A100: 1480 | B100: 45435 | C100: Bob | D100: North | E100: 83318.19 | F100: 22 | G100: Furniture | H100: 3649.13 | I100: 4508.56 | J100: New | K100: 0.16 | L100: Credit Card | M100: Online | N100: =IF(ISBLANK(Table14[[#This Row],[Sales_Rep]]),"Unknown",Table14[[#This Row],[Sales_Rep]]) -> Bob | O100: =PROPER(Table14[[#This Row],[Region]]) -> North | P100: =IF(ISBLANK(Table14[[#This Row],[Sales_Amount]]),MEDIAN(Table14[Sales_Amount]),Table14[[#This Row],[Sales_Amount]]) -> 83318.19 | Q100: =IF(ISBLANK(Table14[[#This Row],[Quantity_Sold]]),MEDIAN(Table14[Quantity_Sold]),Table14[[#This Row],[Quantity_Sold]]) -> 22 | R100: =TRIM(Table14[[#This Row],[Product_Category]]) -> Furniture | S100: =PROPER(Table14[[#This Row],[Customer_Type]]) -> New | T100: =IF(ISBLANK(Table14[[#This Row],[Discount]]),MEDIAN(Table14[Discount]),Table14[[#This Row],[Discount]]) -> 0.16
...

Sheet Retail Sales Orginal
A1: Product_ID | B1: Sale_Date | C1: Sales_Rep | D1: Region | E1: Sales_Amount | F1: Quantity_Sold | G1: Product_Category | H1: Unit_Cost | I1: Unit_Price | J1: Customer_Type | K1: Discount | L1: Payment_Method | M1: Sales_Channel
A2: 1052 | B2: 45235 | C2: David | D2: East | E2: 71951.51 | F2: 48 | G2: Food | H2: 1147.38 | I2: 1594.67 | J2: ReturninG | K2: 0.06 | L2: Credit Card | M2: Retail
A3: 1301 | B3: 45344 | D3: NORTH | E3: 8444.02 | F3: 20 | G3: Electronics | H3: 451.85 | I3: 586.39 | J3: returning | L3: Credit Card | M3: Online
A4: 1426 | B4: 44955 | C4: Charlie | D4: East | F4: 36 | G4: Clothing | H4: 1554.12 | I4: 2130.42 | J4: New | K4: 0.28 | L4: Bank Transfer | M4: Retail
A5: 1170 | B5: 44981 | C5: Eve | D5: West | E5: 73691.05 | G5: Clothing | H5: 1733.8 | I5: 2477.01 | J5: rEturning | K5: 0.15 | L5: Credit Card | M5: Online
A6: 1019 | B6: 45263 | C6: Eve | D6: East | E6: 99978.16 | F6: 33 | G6: Furniture | H6: 2593.01 | I6: 3650.17 | J6: Returning | K6: 0.17 | L6: Credit Card | M6: Retail
A7: 1239 | B7: 45630 | C7: Bob | D7: NORTH | E7: 18064.11 | F7: 12 | G7: Clothing | H7: 1528.85 | I7: 1954.99 | J7: new | K7: 0.23 | L7: Bank Transfer | M7: Retail
A8: 1452 | B8: 45010 | D8: East | E8: 61782.11 | F8: 15 | G8: Food | H8: 4099.54 | I8: 5213.68 | J8: returning | K8: 0.21 | L8: Credit Card | M8: Retail
A9: 1318 | B9: 45124 | C9: Charlie | D9: east | E9: 160204.34 | F9: 45 | G9: Food | H9: 2736.72 | I9: 3747.47 | J9: NeW | L9: Credit Card | M9: Online
A10: 1463 | B10: 45192 | C10: Charlie | D10: East | E10: 29967.11 | F10: 18 | G10: Electronics | H10: 1686.82 | I10: 1935.86 | J10: Returning | L10: Bank Transfer | M10: Online
A11: 1427 | B11: 45297 | C11: Eve | D11: West | E11: 68837.01 | F11: 28 | G11: Food | H11: 2549.57 | I11: 3367.76 | J11: returning | K11: 0.27 | L11: Credit Card | M11: Retail
A12: 1455 | B12: 45319 | C12: David | D12: SOuth | F12: 50 | G12: Clothing | H12: 3254.81 | I12: 4805.11 | J12: ReturninG | K12: 0.17 | L12: Cash | M12: Retail
A13: 1409 | B13: 45318 | D13: South | E13: 4650.09 | G13: Electronics | H13: 3767.42 | I13: 4744.99 | J13: Returning | K13: 0.02 | L13: Cash | M13: Retail
A14: 1169 | B14: 45480 | C14: Eve | D14: WEST | E14: 38774.35 | F14: 49 | G14: Furniture | H14: 803.61 | I14: 976.93 | J14: new | K14: 0.19 | L14: Cash | M14: Retail
A15: 1177 | B15: 45506 | C15: Bob | D15: NORTH | E15: 50873.54 | F15: 15 | G15: Food | H15: 2693.32 | I15: 3768.41 | J15: New | K15: 0.1 | L15: Cash | M15: Online
A16: 1060 | B16: 45151 | C16: David | D16: East | E16: 84654.2 | F16: 27 | G16: Electronics | H16: 3628.69 | I16: 4354.64 | J16: New | K16: 0.28 | L16: Credit Card | M16: Online
A17: 1159 | B17: 44940 | C17: Bob | D17: East | F17: 6 | G17: Electronics | H17: 2645.44 | I17: 3000.09 | J17: ReturninG | K17: 0.15 | L17: Bank Transfer | M17: Online
A18: 1139 | B18: 45154 | C18: David | D18: East | E18: 5218.69 | F18: 2 | G18: Electronics | H18: 2389.48 | I18: 2899.27 | J18: Returning | K18: 0.1 | L18: Bank Transfer | M18: Online
A19: 1053 | B19: 44962 | D19: South | E19: 11615 | F19: 12 | G19: Furniture | H19: 882.08 | I19: 987.67 | J19: New | K19: 0.02 | L19: Bank Transfer | M19: Online
A20: 1426 | B20: 45309 | D20: SOUTH | E20: 25621.81 | F20: 8 | G20: Food | H20: 2968.82 | I20: 4106.06 | J20: Returning | K20: 0.22 | L20: Cash | M20: Online
A21: 1288 | B21: 45369 | C21: David | D21: South | E21: 20271.83 | G21: Electronics | H21: 1329.78 | I21: 1925.15 | J21: returninG | L21: Cash | M21: Online
A22: 1337 | B22: 45445 | C22: Bob | D22: East | E22: 7557.82 | G22: Furniture | H22: 915.83 | I22: 1369.17 | J22: Returning | K22: 0.08 | L22: Bank Transfer | M22: Online
A23: 1319 | B23: 44973 | C23: Eve | D23: East | E23: 112287.09 | F23: 41 | G23: Food | H23: 2844.06 | I23: 3299.65 | J23: New | K23: 0.17 | L23: Cash | M23: Retail
A24: 1205 | B24: 45480 | C24: David | D24: West | E24: 51700.65 | F24: 18 | G24: Furniture | H24: 2763.69 | I24: 3122.02 | J24: New | K24: 0.08 | L24: Cash | M24: Online
A25: 1434 | B25: 45344 | C25: Alice | D25: NORTH | E25: 9329.9 | F25: 6 | G25: Furniture | H25: 1518.93 | I25: 2046.03 | J25: Returning | K25: 0.24 | L25: Bank Transfer | M25: Retail
A26: 1322 | B26: 45003 | C26: Alice | D26: East | E26: 11086.23 | F26: 3 | G26: Furniture | H26: 2993.59 | I26: 4060.89 | J26: New | K26: 0.09 | L26: Bank Transfer | M26: Online
A27: 1165 | B27: 45143 | C27: Charlie | D27: South | E27: 2639.43 | F27: 18 | G27: Furniture | H27: 151.27 | I27: 203.66 | J27: new | K27: 0.28 | L27: Bank Transfer | M27: Retail
A28: 1154 | B28: 45618 | C28: Charlie | D28: West | E28: 26058.24 | F28: 24 | G28: Food | H28: 952.7 | I28: 1392 | J28: New | K28: 0.22 | L28: Bank Transfer | M28: Online
A29: 1103 | B29: 44933 | D29: East | E29: 16454.74 | F29: 6 | G29: Electronics | H29: 2449.66 | I29: 3515.97 | J29: New | K29: 0.22 | L29: Cash | M29: Online
A30: 1003 | B30: 45142 | C30: David | D30: West | E30: 2136.41 | F30: 13 | G30: Electronics | H30: 149.55 | I30: 193.34 | J30: new | K30: 0.15 | L30: Cash | M30: Online
A31: 1067 | B31: 45462 | C31: David | D31: North | E31: 264002.31 | F31: 39 | G31: Clothing | H31: 4707.48 | I31: 6769.29 | J31: Returning | K31: 0 | L31: Credit Card | M31: Retail
A32: 1332 | B32: 45316 | C32: Charlie | D32: East | E32: 48686.3 | F32: 18 | G32: Clothing | H32: 2779.59 | I32: 3298.53 | J32: Returning | K32: 0.18 | L32: Cash | M32: Retail
A33: 1308 | B33: 45051 | C33: David | D33: SOUTH | E33: 6882.52 | F33: 7 | G33: Furniture | H33: 1187.82 | I33: 1365.58 | J33: New | K33: 0.28 | L33: Bank Transfer | M33: Retail
A34: 1421 | B34: 45220 | C34: David | D34: East | E34: 117576.01 | F34: 37 | G34: Furniture | H34: 2209.4 | I34: 3177.73 | J34: Returning | K34: 0 | L34: Bank Transfer | M34: Online
A35: 1088 | B35: 45100 | C35: Alice | D35: west | E35: 3588.45 | F35: 4 | G35: Food | H35: 905.02 | I35: 1196.15 | J35: New | K35: 0.25 | L35: Bank Transfer | M35: Retail
A36: 1166 | B36: 45235 | C36: Charlie | D36: East | E36: 2399.28 | F36: 1 | G36: Clothing | H36: 1991.33 | I36: 2856.29 | J36: new | K36: 0.16 | L36: Bank Transfer | M36: Retail
A37: 1362 | B37: 45068 | C37: Eve | D37: South | E37: 9432.76 | F37: 5 | G37: Furniture | H37: 1527.92 | I37: 2006.97 | J37: New | L37: Cash | M37: Retail
A38: 1311 | B38: 45396 | C38: Charlie | D38: South | F38: 39 | G38: Clothing | H38: 3976.45 | I38: 5201.72 | J38: New | K38: 0.18 | L38: Cash | M38: Online
A39: 1038 | B39: 45406 | C39: Eve | D39: West | F39: 24 | G39: Electronics | H39: 2282.47 | I39: 2558.37 | J39: Returning | K39: 0.02 | L39: Cash | M39: Retail
A40: 1001 | B40: 45614 | C40: Alice | D40: West | E40: 56953.67 | F40: 19 | G40: Electronics | H40: 3366.81 | I40: 4163.28 | J40: New | K40: 0.28 | L40: Credit Card | M40: Retail
A41: 1184 | B41: 44941 | C41: Bob | D41: South | E41: 164921.02 | F41: 49 | G41: Furniture | H41: 3039.91 | I41: 3619.07 | J41: New | K41: 0.07 | L41: Bank Transfer | M41: Retail
A42: 1147 | B42: 44969 | D42: East | E42: 20392.21 | F42: 14 | G42: Food | H42: 1739.24 | I42: 2051.53 | J42: Returning | K42: 0.29 | L42: Bank Transfer | M42: Retail
A43: 1252 | B43: 45471 | D43: West | E43: 16437.78 | F43: 20 | G43: Clothing | H43: 770.05 | I43: 874.35 | J43: New | K43: 0.06 | L43: Bank Transfer | M43: Retail
A44: 1032 | B44: 45220 | C44: David | D44: West | E44: 24970.36 | F44: 11 | G44: Electronics | H44: 1844.37 | I44: 2316.36 | J44: Returning | K44: 0.02 | L44: Bank Transfer | M44: Online
A45: 1402 | B45: 45610 | C45: Bob | D45: East | E45: 31145.14 | F45: 44 | G45: Clothing | H45: 638.38 | I45: 722.29 | J45: Returning | K45: 0.02 | L45: Credit Card | M45: Online
A46: 1036 | B46: 45012 | C46: Bob | D46: East | E46: 7451.08 | F46: 7 | G46: Furniture | H46: 770.86 | I46: 1064.44 | J46: returning | K46: 0 | L46: Bank Transfer | M46: Online
A47: 1323 | B47: 45427 | C47: Alice | D47: South | E47: 168954.62 | F47: 36 | G47: Furniture | H47: 4420.25 | I47: 5866.48 | J47: Returning | K47: 0.2 | L47: Cash | M47: Retail
A48: 1371 | B48: 45468 | C48: Bob | D48: South | E48: 69836.41 | F48: 25 | G48: Furniture | H48: 2779.29 | I48: 3365.61 | J48: Returning | K48: 0.17 | L48: Bank Transfer | M48: Retail
A49: 1116 | B49: 45378 | C49: Eve | D49: North | E49: 108442.32 | F49: 38 | G49: Electronics | H49: 3097.56 | I49: 3909.24 | J49: New | K49: 0.27 | L49: Cash | M49: Retail
A50: 1260 | B50: 45493 | C50: Bob | D50: East | E50: 57719.28 | F50: 39 | G50: Furniture | H50: 1448.19 | I50: 2055.53 | J50: new | K50: 0.28 | L50: Bank Transfer | M50: Online
A51: 1119 | B51: 45433 | C51: David | D51: South | F51: 19 | G51: Electronics | H51: 3733.7 | I51: 5453.97 | J51: New | K51: 0.2 | L51: Bank Transfer | M51: Online
A52: 1226 | B52: 45530 | C52: David | D52: SOUTH | E52: 10598.2 | F52: 48 | G52: Clothing | H52: 233.02 | I52: 302.46 | J52: Returning | K52: 0.27 | L52: Cash | M52: Retail
A53: 1106 | B53: 45069 | C53: David | D53: North | E53: 48260.93 | F53: 11 | G53: Food | H53: 4331.17 | I53: 5416.49 | J53: Returning | K53: 0.19 | L53: Credit Card | M53: Retail
A54: 1294 | B54: 45446 | C54: David | D54: South | E54: 118546.45 | F54: 40 | G54: Furniture | H54: 2685.46 | I54: 3751.47 | J54: New | K54: 0.21 | L54: Bank Transfer | M54: Online
A55: 1271 | B55: 45330 | C55: Eve | D55: North | E55: 94771.99 | F55: 39 | G55: Clothing | H55: 2611.47 | I55: 3115.45 | J55: New | K55: 0.22 | L55: Cash | M55: Retail
A56: 1272 | B56: 44961 | C56: Charlie | D56: South | E56: 143250.5 | F56: 33 | G56: Furniture | H56: 4294.12 | I56: 5293.81 | J56: Returning | K56: 0.18 | L56: Bank Transfer | M56: Online
A57: 1165 | B57: 45136 | D57: South | E57: 105479.39 | F57: 23 | G57: Furniture | H57: 4839.78 | I57: 6034.29 | J57: New | K57: 0.24 | L57: Bank Transfer | M57: Retail
A58: 1217 | B58: 45377 | C58: David | D58: North | E58: 30387.24 | F58: 10 | G58: Furniture | H58: 2608.73 | I58: 3533.4 | J58: New | K58: 0.14 | L58: Credit Card | M58: Online
A59: 1423 | B59: 44999 | C59: Bob | D59: West | E59: 62067.63 | F59: 19 | G59: Clothing | H59: 2479.66 | I59: 3438.65 | J59: New | K59: 0.05 | L59: Cash | M59: Retail
A60: 1411 | B60: 45348 | C60: David | D60: North | E60: 108544.26 | F60: 21 | G60: Clothing | H60: 3674.06 | I60: 5384.14 | J60: Returning | K60: 0.04 | L60: Credit Card | M60: Retail
A61: 1055 | B61: 45566 | C61: Bob | D61: North | E61: 61285.86 | G61: Food | H61: 3490.27 | I61: 4559.96 | J61: New | K61: 0.16 | L61: Cash | M61: Retail
A62: 1299 | B62: 45323 | C62: Bob | D62: West | E62: 49958.77 | F62: 30 | G62: Furniture | H62: 1483.07 | I62: 2134.99 | J62: Returning | K62: 0.22 | L62: Credit Card | M62: Retail
A63: 1015 | B63: 44945 | C63: David | D63: South | E63: 22601.17 | F63: 11 | G63: Furniture | H63: 1486.57 | I63: 2185.8 | J63: New | L63: Bank Transfer | M63: Online
A64: 1179 | B64: 45580 | C64: Eve | D64: East | E64: 125020.4 | F64: 26 | G64: Electronics | H64: 4254.54 | I64: 5008.83 | J64: Returning | L64: Cash | M64: Retail
A65: 1483 | B65: 45513 | C65: Bob | D65: North | E65: 56717.43 | F65: 26 | G65: Clothing | H65: 1983.32 | I65: 2371.13 | J65: Returning | K65: 0.08 | L65: Cash | M65: Online
A66: 1358 | B66: 45149 | C66: Bob | D66: East | E66: 5824.44 | F66: 4 | G66: Clothing | H66: 1338.02 | I66: 1754.35 | J66: Returning | K66: 0.17 | L66: Bank Transfer | M66: Online
A67: 1322 | B67: 45594 | C67: David | D67: East | E67: 92796.02 | F67: 26 | G67: Furniture | H67: 3470.09 | I67: 5026.87 | J67: New | K67: 0.29 | L67: Bank Transfer | M67: Retail
A68: 1173 | B68: 45297 | C68: Bob | D68: North | E68: 1677.08 | F68: 2 | G68: Clothing | H68: 742.52 | I68: 873.48 | J68: Returning | K68: 0.04 | L68: Bank Transfer | M68: Retail
A69: 1233 | B69: 45218 | C69: Bob | D69: West | E69: 1041.78 | F69: 1 | G69: Electronics | H69: 865.93 | I69: 1144.81 | J69: New | K69: 0.09 | L69: Credit Card | M69: Online
A70: 1452 | B70: 45060 | C70: David | D70: East | F70: 29 | G70: Furniture | H70: 4954.07 | I70: 7017.06 | J70: New | K70: 0.3 | L70: Cash | M70: Online
A71: 1361 | B71: 45588 | C71: David | D71: North | F71: 8 | G71: Food | H71: 1363.39 | I71: 1981.6 | J71: Returning | K71: 0.17 | L71: Credit Card | M71: Online
A72: 1402 | B72: 45183 | C72: Alice | D72: West | E72: 119838.05 | F72: 29 | G72: Clothing | H72: 3728.06 | I72: 4919.46 | J72: Returning | K72: 0.16 | L72: Credit Card | M72: Retail
A73: 1254 | B73: 45036 | C73: Eve | D73: South | E73: 165705.75 | F73: 50 | G73: Clothing | H73: 3686.78 | I73: 4091.5 | J73: Returning | K73: 0.19 | L73: Cash | M73: Online
A74: 1224 | B74: 45174 | C74: Eve | D74: East | E74: 240585.97 | F74: 44 | G74: Food | H74: 4497.34 | I74: 6284.9 | J74: New | K74: 0.13 | L74: Credit Card | M74: Retail
A75: 1303 | B75: 45054 | C75: Bob | D75: North | E75: 54405.76 | F75: 40 | G75: Electronics | H75: 1151.16 | I75: 1679.19 | J75: Returning | K75: 0.19 | L75: Bank Transfer | M75: Online
A76: 1219 | B76: 45039 | C76: Eve | D76: West | E76: 184386.15 | F76: 50 | G76: Clothing | H76: 3267.79 | I76: 4288.05 | J76: New | K76: 0.14 | L76: Bank Transfer | M76: Online
A77: 1080 | B77: 45090 | C77: Bob | D77: North | E77: 170038.41 | F77: 31 | G77: Clothing | H77: 3873.58 | I77: 5773.8 | J77: New | K77: 0.05 | L77: Cash | M77: Online
A78: 1159 | B78: 45516 | C78: Alice | D78: North | E78: 63436.59 | F78: 28 | G78: Clothing | H78: 1758.65 | I78: 2634.41 | J78: New | K78: 0.14 | L78: Bank Transfer | M78: Online
A79: 1066 | B79: 45141 | C79: David | D79: North | E79: 19792.09 | F79: 28 | G79: Clothing | H79: 754.24 | I79: 894.76 | J79: New | K79: 0.21 | L79: Credit Card | M79: Online
A80: 1302 | B80: 45315 | C80: David | D80: West | E80: 102265.87 | F80: 33 | G80: Furniture | H80: 2323.16 | I80: 3162.21 | J80: New | K80: 0.02 | L80: Cash | M80: Retail
A81: 1148 | B81: 45217 | D81: North | E81: 121832.4 | F81: 50 | G81: Clothing | H81: 2346.51 | I81: 3045.81 | J81: New | K81: 0.2 | L81: Credit Card | M81: Retail
A82: 1197 | B82: 45037 | C82: Eve | D82: North | E82: 64521.8 | F82: 38 | G82: Furniture | H82: 1623.03 | I82: 1907.8 | J82: Returning | K82: 0.11 | L82: Cash | M82: Retail
A83: 1159 | B83: 45130 | C83: Alice | D83: South | E83: 19436.73 | F83: 48 | G83: Food | H83: 305.69 | I83: 444.98 | J83: Returning | K83: 0.09 | L83: Credit Card | M83: Retail
A84: 1110 | B84: 45507 | C84: Eve | D84: North | E84: 20761.68 | F84: 7 | G84: Food | H84: 2437.05 | I84: 3155.27 | J84: Returning | K84: 0.06 | L84: Bank Transfer | M84: Online
A85: 1154 | B85: 45274 | C85: Eve | D85: North | E85: 203247.37 | F85: 49 | G85: Clothing | H85: 4172.68 | I85: 5760.98 | J85: Returning | K85: 0.28 | L85: Bank Transfer | M85: Retail
A86: 1490 | B86: 45321 | C86: Alice | D86: West | F86: 27 | G86: Food | H86: 4796.56 | I86: 6882.36 | J86: Returning | K86: 0.3 | L86: Bank Transfer | M86: Online
A87: 1224 | B87: 44985 | C87: Alice | D87: East | F87: 46 | G87: Clothing | H87: 830 | I87: 1026.55 | J87: Returning | L87: Cash | M87: Retail
A88: 1143 | B88: 45291 | C88: Alice | D88: West | E88: 131360.78 | F88: 50 | G88: Furniture | H88: 2365.38 | I88: 3165.32 | J88: Returning | L88: Bank Transfer | M88: Retail
A89: 1431 | B89: 45377 | C89: Alice | D89: North | E89: 84527.35 | F89: 21 | G89: Food | H89: 3763.71 | I89: 4236.96 | J89: Returning | K89: 0.05 | L89: Bank Transfer | M89: Retail
A90: 1071 | B90: 45272 | C90: David | D90: West | E90: 9866.88 | F90: 12 | G90: Food | H90: 591.86 | I90: 839.02 | J90: New | K90: 0.02 | L90: Credit Card | M90: Online
A91: 1125 | B91: 45418 | C91: Charlie | D91: East | E91: 72239.76 | F91: 15 | G91: Clothing | H91: 4919.18 | I91: 5802.39 | J91: Returning | K91: 0.17 | L91: Credit Card | M91: Retail
A92: 1335 | B92: 45032 | C92: Charlie | D92: North | E92: 147801.78 | F92: 36 | G92: Clothing | H92: 3898.11 | I92: 5474.14 | J92: New | K92: 0.25 | L92: Bank Transfer | M92: Retail
A93: 1258 | B93: 45526 | C93: Alice | D93: West | E93: 148353.75 | F93: 48 | G93: Electronics | H93: 2408.92 | I93: 3359.46 | J93: Returning | K93: 0.08 | L93: Cash | M93: Retail
A94: 1062 | B94: 45234 | C94: Charlie | D94: South | E94: 64148.57 | F94: 17 | G94: Food | H94: 3323.14 | I94: 3890.15 | J94: New | K94: 0.03 | L94: Bank Transfer | M94: Retail
A95: 1477 | B95: 44997 | C95: Charlie | D95: East | E95: 62587.92 | F95: 14 | G95: Electronics | H95: 4274.77 | I95: 4807.06 | J95: Returning | K95: 0.07 | L95: Cash | M95: Online
A96: 1395 | B96: 44981 | C96: Alice | D96: South | F96: 13 | G96: Food | H96: 3800.09 | I96: 4369.48 | J96: New | K96: 0.21 | L96: Cash | M96: Retail
A97: 1084 | B97: 45138 | C97: Charlie | D97: East | F97: 7 | G97: Food | H97: 90.87 | I97: 132.25 | J97: Returning | K97: 0.05 | L97: Cash | M97: Retail
A98: 1017 | B98: 44987 | C98: Eve | D98: West | E98: 116881.32 | F98: 34 | G98: Furniture | H98: 4168.23 | I98: 4910.98 | J98: Returning | K98: 0.3 | L98: Cash | M98: Retail
A99: 1033 | B99: 45393 | C99: Bob | D99: West | E99: 170058.7 | F99: 37 | G99: Electronics | H99: 3929.13 | I99: 5892.54 | J99: New | K99: 0.22 | L99: Credit Card | M99: Online
A100: 1480 | B100: 45435 | C100: Bob | D100: North | E100: 83318.19 | F100: 22 | G100: Furniture | H100: 3649.13 | I100: 4508.56 | J100: New | K100: 0.16 | L100: Credit Card | M100: Online
...

Sheet Sales distribution by sales
A3: Row Labels | B3: Sum of Sales_Amount
A4: Online | B4: 1.5723348e+08
A5: Retail | B5: 1.6361764e+08
A6: Grand Total | B6: 3.2085111e+08

Sheet Sales by product category
A3: Row Labels | B3: Sum of Sales_Amount
A4: Clothing | B4: 77185506
A5: Electronics | B5: 83820170
A6: Food | B6: 80821503
A7: Furniture | B7: 79023937
A8: Grand Total | B8: 3.2085111e+08

Sheet Sales by Region
A3: Row Labels | B3: Sum of Sales_Amount
A4: East | B4: 80523580
A5: North | B5: 79846782
A6: South | B6: 78136684
A7: West | B7: 82344069
A8: Grand Total | B8: 3.2085111e+08

Sheet Customer Type distribution
A3: Row Labels | B3: Sum of Sales_Amount
A4: New | B4: 1.5821566e+08
A5: Returning | B5: 1.6263545e+08
A6: Grand Total | B6: 3.2085111e+08

Sheet Monthly Sales Trend
A3: Row Labels | B3: Sum of Sales_Amount
A4: Jan | B4: 30338903
A5: Feb | B5: 23542181
A6: Mar | B6: 28829168
A7: Apr | B7: 25476027
A8: May | B8: 24067324
A9: Jun | B9: 28210504
A10: Jul | B10: 25140302
A11: Aug | B11: 30011233
A12: Sep | B12: 24926259
A13: Oct | B13: 28188442
A14: Nov | B14: 27873304
A15: Dec | B15: 24247467
A16: Grand Total | B16: 3.2085111e+08

Sheet Region sales by customer type
A3: Sum of Sales_Amount | B3: Column Labels
A4: Row Labels | B4: New | C4: Returning | D4: Grand Total
A5: East | B5: 40172249 | C5: 40351331 | D5: 80523580
A6: North | B6: 36887553 | C6: 42959229 | D6: 79846782
A7: South | B7: 40144253 | C7: 37992431 | D7: 78136684
A8: West | B8: 41011606 | C8: 41332463 | D8: 82344069
A9: Grand Total | B9: 1.5821566e+08 | C9: 1.6263545e+08 | D9: 3.2085111e+08
